{
"meta":{"test_sets":[],"test_metrics":[],"learn_metrics":[{"best_value":"Min","name":"Tweedie:variance_power=1.5"}],"launch_mode":"Train","parameters":"","iteration_count":1000,"learn_sets":["learn"],"name":"experiment"},
"iterations":[
{"learn":[10.94351843],"iteration":0,"passed_time":0.01082434216,"remaining_time":10.81351782},
{"learn":[10.94351391],"iteration":1,"passed_time":0.02806098698,"remaining_time":14.0024325},
{"learn":[10.94350943],"iteration":2,"passed_time":0.04677072617,"remaining_time":15.54347133},
{"learn":[10.94350421],"iteration":3,"passed_time":0.06977404406,"remaining_time":17.37373697},
{"learn":[10.9434998],"iteration":4,"passed_time":0.08804575218,"remaining_time":17.52110468},
{"learn":[10.94349539],"iteration":5,"passed_time":0.1037005419,"remaining_time":17.17972311},
{"learn":[10.94349097],"iteration":6,"passed_time":0.1241999195,"remaining_time":17.61864572},
{"learn":[10.94348655],"iteration":7,"passed_time":0.1420861948,"remaining_time":17.61868815},
{"learn":[10.94348203],"iteration":8,"passed_time":0.165072492,"remaining_time":18.17631551},
{"learn":[10.94347754],"iteration":9,"passed_time":0.1879396708,"remaining_time":18.60602741},
{"learn":[10.94347307],"iteration":10,"passed_time":0.2063126723,"remaining_time":18.54938481},
{"learn":[10.94346867],"iteration":11,"passed_time":0.2225749163,"remaining_time":18.32533477},
{"learn":[10.94346426],"iteration":12,"passed_time":0.2416356747,"remaining_time":18.34572392},
{"learn":[10.94345983],"iteration":13,"passed_time":0.2655004815,"remaining_time":18.69881962},
{"learn":[10.94345542],"iteration":14,"passed_time":0.2858077097,"remaining_time":18.7680396},
{"learn":[10.94345096],"iteration":15,"passed_time":0.3081866459,"remaining_time":18.95347873},
{"learn":[10.94344656],"iteration":16,"passed_time":0.3278881445,"remaining_time":18.95964977},
{"learn":[10.94344208],"iteration":17,"passed_time":0.3496075084,"remaining_time":19.07303185},
{"learn":[10.94343768],"iteration":18,"passed_time":0.3687569516,"remaining_time":19.03950366},
{"learn":[10.94343327],"iteration":19,"passed_time":0.3877722766,"remaining_time":19.00084155},
{"learn":[10.94342881],"iteration":20,"passed_time":0.409489694,"remaining_time":19.09001954},
{"learn":[10.94342441],"iteration":21,"passed_time":0.4297579624,"remaining_time":19.10469487},
{"learn":[10.94341995],"iteration":22,"passed_time":0.4502966403,"remaining_time":19.12781815},
{"learn":[10.94341552],"iteration":23,"passed_time":0.4737164668,"remaining_time":19.26446965},
{"learn":[10.94341112],"iteration":24,"passed_time":0.492919184,"remaining_time":19.22384818},
{"learn":[10.94340671],"iteration":25,"passed_time":0.5125852255,"remaining_time":19.20223114},
{"learn":[10.94340229],"iteration":26,"passed_time":0.5340819067,"remaining_time":19.24672945},
{"learn":[10.94339788],"iteration":27,"passed_time":0.5565742568,"remaining_time":19.32107777},
{"learn":[10.94339347],"iteration":28,"passed_time":0.5758632113,"remaining_time":19.2814889},
{"learn":[10.94338907],"iteration":29,"passed_time":0.5954830313,"remaining_time":19.25395135},
{"learn":[10.94338466],"iteration":30,"passed_time":0.6131686292,"remaining_time":19.16646457},
{"learn":[10.9433802],"iteration":31,"passed_time":0.6317231018,"remaining_time":19.10962383},
{"learn":[10.94337574],"iteration":32,"passed_time":0.6500606598,"remaining_time":19.04874721},
{"learn":[10.94337048],"iteration":33,"passed_time":0.6709562935,"remaining_time":19.06305234},
{"learn":[10.94336603],"iteration":34,"passed_time":0.6879828851,"remaining_time":18.96867098},
{"learn":[10.94336158],"iteration":35,"passed_time":0.7044863324,"remaining_time":18.86457846},
{"learn":[10.94335718],"iteration":36,"passed_time":0.7189098424,"remaining_time":18.7110859},
{"learn":[10.94335247],"iteration":37,"passed_time":0.7391547904,"remaining_time":18.71228706},
{"learn":[10.94334787],"iteration":38,"passed_time":0.7574894535,"remaining_time":18.66531705},
{"learn":[10.94334345],"iteration":39,"passed_time":0.7786112498,"remaining_time":18.68667},
{"learn":[10.94333773],"iteration":40,"passed_time":0.7996267238,"remaining_time":18.7034641},
{"learn":[10.94333332],"iteration":41,"passed_time":0.8162556572,"remaining_time":18.61840285},
{"learn":[10.94332886],"iteration":42,"passed_time":0.8348782106,"remaining_time":18.58089413},
{"learn":[10.94332437],"iteration":43,"passed_time":0.8637072671,"remaining_time":18.76600335},
{"learn":[10.94331997],"iteration":44,"passed_time":0.8834416893,"remaining_time":18.74859585},
{"learn":[10.9433148],"iteration":45,"passed_time":0.9049528306,"remaining_time":18.76793479},
{"learn":[10.9433104],"iteration":46,"passed_time":0.9233309289,"remaining_time":18.72200798},
{"learn":[10.94330599],"iteration":47,"passed_time":0.9436418002,"remaining_time":18.71556237},
{"learn":[10.94330056],"iteration":48,"passed_time":0.9683713594,"remaining_time":18.79430945},
{"learn":[10.94329616],"iteration":49,"passed_time":0.9856222342,"remaining_time":18.72682245},
{"learn":[10.94329169],"iteration":50,"passed_time":1.002835544,"remaining_time":18.6606065},
{"learn":[10.94328729],"iteration":51,"passed_time":1.018516145,"remaining_time":18.5683328},
{"learn":[10.94328288],"iteration":52,"passed_time":1.034345219,"remaining_time":18.48160232},
{"learn":[10.94327843],"iteration":53,"passed_time":1.052541323,"remaining_time":18.43896466},
{"learn":[10.94327394],"iteration":54,"passed_time":1.075701423,"remaining_time":18.48250627},
{"learn":[10.94326949],"iteration":55,"passed_time":1.093464604,"remaining_time":18.43268903},
{"learn":[10.94326509],"iteration":56,"passed_time":1.109389126,"remaining_time":18.353578},
{"learn":[10.94326068],"iteration":57,"passed_time":1.124724648,"remaining_time":18.26707963},
{"learn":[10.94325628],"iteration":58,"passed_time":1.139935072,"remaining_time":18.18099835},
{"learn":[10.94325187],"iteration":59,"passed_time":1.154729804,"remaining_time":18.09076693},
{"learn":[10.94324747],"iteration":60,"passed_time":1.168912894,"remaining_time":17.99359357},
{"learn":[10.94324306],"iteration":61,"passed_time":1.183535349,"remaining_time":17.90574447},
{"learn":[10.94323866],"iteration":62,"passed_time":1.19862428,"remaining_time":17.82715794},
{"learn":[10.94323267],"iteration":63,"passed_time":1.218437667,"remaining_time":17.81965088},
{"learn":[10.9432268],"iteration":64,"passed_time":1.251280245,"remaining_time":17.99918506},
{"learn":[10.94322238],"iteration":65,"passed_time":1.270530529,"remaining_time":17.97993203},
{"learn":[10.94321794],"iteration":66,"passed_time":1.290620609,"remaining_time":17.97237355},
{"learn":[10.94321332],"iteration":67,"passed_time":1.310112596,"remaining_time":17.9562491},
{"learn":[10.94320886],"iteration":68,"passed_time":1.327213535,"remaining_time":17.90776524},
{"learn":[10.94320443],"iteration":69,"passed_time":1.345029277,"remaining_time":17.86967468},
{"learn":[10.94319998],"iteration":70,"passed_time":1.360533159,"remaining_time":17.80190571},
{"learn":[10.94319558],"iteration":71,"passed_time":1.375121938,"remaining_time":17.72379387},
{"learn":[10.94319117],"iteration":72,"passed_time":1.390636472,"remaining_time":17.65917821},
{"learn":[10.94318674],"iteration":73,"passed_time":1.406088986,"remaining_time":17.59511353},
{"learn":[10.94318234],"iteration":74,"passed_time":1.421354462,"remaining_time":17.53003836},
{"learn":[10.94317793],"iteration":75,"passed_time":1.438473726,"remaining_time":17.48881214},
{"learn":[10.94317352],"iteration":76,"passed_time":1.454039043,"remaining_time":17.4295849},
{"learn":[10.94316912],"iteration":77,"passed_time":1.46874929,"remaining_time":17.36136981},
{"learn":[10.94316449],"iteration":78,"passed_time":1.488127943,"remaining_time":17.34893462},
{"learn":[10.94316008],"iteration":79,"passed_time":1.503841514,"remaining_time":17.29417742},
{"learn":[10.94315567],"iteration":80,"passed_time":1.519261107,"remaining_time":17.23704886},
{"learn":[10.94315126],"iteration":81,"passed_time":1.540365624,"remaining_time":17.24458101},
{"learn":[10.94314686],"iteration":82,"passed_time":1.559114825,"remaining_time":17.22540113},
{"learn":[10.94314245],"iteration":83,"passed_time":1.573458692,"remaining_time":17.15819241},
{"learn":[10.94313795],"iteration":84,"passed_time":1.59102532,"remaining_time":17.12691962},
{"learn":[10.9431334],"iteration":85,"passed_time":1.611473515,"remaining_time":17.12659062},
{"learn":[10.94312899],"iteration":86,"passed_time":1.626758726,"remaining_time":17.07161744},
{"learn":[10.94312452],"iteration":87,"passed_time":1.642832756,"remaining_time":17.02572129},
{"learn":[10.94312012],"iteration":88,"passed_time":1.657233329,"remaining_time":16.96336588},
{"learn":[10.94311503],"iteration":89,"passed_time":1.673644389,"remaining_time":16.92240438},
{"learn":[10.94311053],"iteration":90,"passed_time":1.692517043,"remaining_time":16.90657134},
{"learn":[10.94310613],"iteration":91,"passed_time":1.706743128,"remaining_time":16.84481262},
{"learn":[10.94310172],"iteration":92,"passed_time":1.72120988,"remaining_time":16.78642324},
{"learn":[10.94309715],"iteration":93,"passed_time":1.742052695,"remaining_time":16.79042279},
{"learn":[10.94309275],"iteration":94,"passed_time":1.756662182,"remaining_time":16.73451868},
{"learn":[10.94308834],"iteration":95,"passed_time":1.771180953,"remaining_time":16.67862064},
{"learn":[10.9430831],"iteration":96,"passed_time":1.789885408,"remaining_time":16.66254147},
{"learn":[10.94307867],"iteration":97,"passed_time":1.805165753,"remaining_time":16.61489295},
{"learn":[10.94307421],"iteration":98,"passed_time":1.821906971,"remaining_time":16.58119375},
{"learn":[10.94306974],"iteration":99,"passed_time":1.838335693,"remaining_time":16.54502123},
{"learn":[10.94306534],"iteration":100,"passed_time":1.853598343,"remaining_time":16.4988605},
{"learn":[10.94306093],"iteration":101,"passed_time":1.868328823,"remaining_time":16.44862042},
{"learn":[10.94305647],"iteration":102,"passed_time":1.886456767,"remaining_time":16.42865748},
{"learn":[10.94305207],"iteration":103,"passed_time":1.903821566,"remaining_time":16.40215503},
{"learn":[10.94304662],"iteration":104,"passed_time":1.925711212,"remaining_time":16.41439557},
{"learn":[10.9430415],"iteration":105,"passed_time":1.941412791,"remaining_time":16.37380222},
{"learn":[10.9430367],"iteration":106,"passed_time":1.961385887,"remaining_time":16.36932334},
{"learn":[10.94303229],"iteration":107,"passed_time":1.977274215,"remaining_time":16.33082037},
{"learn":[10.94302786],"iteration":108,"passed_time":1.993146292,"remaining_time":16.2925995},
{"learn":[10.94302333],"iteration":109,"passed_time":2.011477176,"remaining_time":16.27467897},
{"learn":[10.94301883],"iteration":110,"passed_time":2.030070891,"remaining_time":16.25885605},
{"learn":[10.94301443],"iteration":111,"passed_time":2.044387323,"remaining_time":16.20907092},
{"learn":[10.94301002],"iteration":112,"passed_time":2.058605513,"remaining_time":16.15914239},
{"learn":[10.94300562],"iteration":113,"passed_time":2.074417897,"remaining_time":16.12223032},
{"learn":[10.94300119],"iteration":114,"passed_time":2.090202983,"remaining_time":16.08547513},
{"learn":[10.94299677],"iteration":115,"passed_time":2.107086811,"remaining_time":16.05745466},
{"learn":[10.94299236],"iteration":116,"passed_time":2.122055193,"remaining_time":16.01516868},
{"learn":[10.94298796],"iteration":117,"passed_time":2.137814034,"remaining_time":15.97925405},
{"learn":[10.94298348],"iteration":118,"passed_time":2.156409485,"remaining_time":15.96467862},
{"learn":[10.94297898],"iteration":119,"passed_time":2.174791268,"remaining_time":15.9484693},
{"learn":[10.94297458],"iteration":120,"passed_time":2.190740604,"remaining_time":15.91455364},
{"learn":[10.94297017],"iteration":121,"passed_time":2.207581775,"remaining_time":15.88735081},
{"learn":[10.94296577],"iteration":122,"passed_time":2.223521694,"remaining_time":15.85389046},
{"learn":[10.94296132],"iteration":123,"passed_time":2.243240312,"remaining_time":15.84740736},
{"learn":[10.94295691],"iteration":124,"passed_time":2.260196762,"remaining_time":15.82137733},
{"learn":[10.94295251],"iteration":125,"passed_time":2.276125771,"remaining_time":15.78836447},
{"learn":[10.94294807],"iteration":126,"passed_time":2.292593459,"remaining_time":15.75932354},
{"learn":[10.94294367],"iteration":127,"passed_time":2.307698187,"remaining_time":15.7211939},
{"learn":[10.94293924],"iteration":128,"passed_time":2.323625619,"remaining_time":15.68897608},
{"learn":[10.94293484],"iteration":129,"passed_time":2.338140665,"remaining_time":15.64755676},
{"learn":[10.94293031],"iteration":130,"passed_time":2.354501932,"remaining_time":15.61879526},
{"learn":[10.9429259],"iteration":131,"passed_time":2.369828694,"remaining_time":15.58341899},
{"learn":[10.9429215],"iteration":132,"passed_time":2.384823581,"remaining_time":15.54618079},
{"learn":[10.94291709],"iteration":133,"passed_time":2.400732909,"remaining_time":15.51518432},
{"learn":[10.94291257],"iteration":134,"passed_time":2.42366815,"remaining_time":15.52942925},
{"learn":[10.94290748],"iteration":135,"passed_time":2.445435259,"remaining_time":15.53570635},
{"learn":[10.94290237],"iteration":136,"passed_time":2.466181443,"remaining_time":15.53514296},
{"learn":[10.94289796],"iteration":137,"passed_time":2.480705955,"remaining_time":15.49542416},
{"learn":[10.94289354],"iteration":138,"passed_time":2.496171949,"remaining_time":15.46189963},
{"learn":[10.94288913],"iteration":139,"passed_time":2.511403199,"remaining_time":15.42719108},
{"learn":[10.94288443],"iteration":140,"passed_time":2.530291688,"remaining_time":15.41503943},
{"learn":[10.94288002],"iteration":141,"passed_time":2.545869216,"remaining_time":15.38278724},
{"learn":[10.94287562],"iteration":142,"passed_time":2.560425665,"remaining_time":15.34464892},
{"learn":[10.94286989],"iteration":143,"passed_time":2.577494685,"remaining_time":15.32177396},
{"learn":[10.94286549],"iteration":144,"passed_time":2.5917362,"remaining_time":15.28230656},
{"learn":[10.94286092],"iteration":145,"passed_time":2.612795629,"remaining_time":15.28306484},
{"learn":[10.94285652],"iteration":146,"passed_time":2.627359423,"remaining_time":15.24583393},
{"learn":[10.94285211],"iteration":147,"passed_time":2.641878645,"remaining_time":15.20865274},
{"learn":[10.94284763],"iteration":148,"passed_time":2.658248953,"remaining_time":15.18234805},
{"learn":[10.94284304],"iteration":149,"passed_time":2.673425336,"remaining_time":15.14941024},
{"learn":[10.94283863],"iteration":150,"passed_time":2.687902937,"remaining_time":15.11277876},
{"learn":[10.94283351],"iteration":151,"passed_time":2.703567481,"remaining_time":15.08306068},
{"learn":[10.942829],"iteration":152,"passed_time":2.722147735,"remaining_time":15.06966753},
{"learn":[10.94282441],"iteration":153,"passed_time":2.7374472,"remaining_time":15.03818397},
{"learn":[10.9428198],"iteration":154,"passed_time":2.75893147,"remaining_time":15.0406264},
{"learn":[10.94281535],"iteration":155,"passed_time":2.777007547,"remaining_time":15.02432288},
{"learn":[10.9428109],"iteration":156,"passed_time":2.792343956,"remaining_time":14.99328634},
{"learn":[10.9428065],"iteration":157,"passed_time":2.806844497,"remaining_time":14.95799409},
{"learn":[10.94280209],"iteration":158,"passed_time":2.823439629,"remaining_time":14.93404232},
{"learn":[10.94279678],"iteration":159,"passed_time":2.840052078,"remaining_time":14.91027341},
{"learn":[10.94279159],"iteration":160,"passed_time":2.857652634,"remaining_time":14.89174261},
{"learn":[10.94278712],"iteration":161,"passed_time":2.875350274,"remaining_time":14.87372549},
{"learn":[10.94278259],"iteration":162,"passed_time":2.895828099,"remaining_time":14.86998846},
{"learn":[10.94277811],"iteration":163,"passed_time":2.911286466,"remaining_time":14.84046028},
{"learn":[10.94277283],"iteration":164,"passed_time":2.930007142,"remaining_time":14.8276119},
{"learn":[10.94276825],"iteration":165,"passed_time":2.949046805,"remaining_time":14.81629539},
{"learn":[10.9427638],"iteration":166,"passed_time":2.967126016,"remaining_time":14.80009564},
{"learn":[10.94275925],"iteration":167,"passed_time":2.983849773,"remaining_time":14.77716078},
{"learn":[10.94275485],"iteration":168,"passed_time":2.998598764,"remaining_time":14.74458919},
{"learn":[10.94275032],"iteration":169,"passed_time":3.015152121,"remaining_time":14.72103683},
{"learn":[10.94274591],"iteration":170,"passed_time":3.035079665,"remaining_time":14.71392422},
{"learn":[10.94274146],"iteration":171,"passed_time":3.054710141,"remaining_time":14.70523254},
{"learn":[10.94273699],"iteration":172,"passed_time":3.070407046,"remaining_time":14.67761056},
{"learn":[10.94273259],"iteration":173,"passed_time":3.085157344,"remaining_time":14.64563199},
{"learn":[10.94272818],"iteration":174,"passed_time":3.100718807,"remaining_time":14.61767437},
{"learn":[10.94272367],"iteration":175,"passed_time":3.118675977,"remaining_time":14.60107389},
{"learn":[10.94271926],"iteration":176,"passed_time":3.133260815,"remaining_time":14.56877769},
{"learn":[10.94271486],"iteration":177,"passed_time":3.148187294,"remaining_time":14.53825818},
{"learn":[10.9427104],"iteration":178,"passed_time":3.165485189,"remaining_time":14.51878961},
{"learn":[10.94270596],"iteration":179,"passed_time":3.183042586,"remaining_time":14.50052733},
{"learn":[10.94270156],"iteration":180,"passed_time":3.199523819,"remaining_time":14.47740336},
{"learn":[10.9426963],"iteration":181,"passed_time":3.219209169,"remaining_time":14.4687533},
{"learn":[10.94269176],"iteration":182,"passed_time":3.239676991,"remaining_time":14.46347597},
{"learn":[10.94268729],"iteration":183,"passed_time":3.259439728,"remaining_time":14.45490662},
{"learn":[10.94268288],"iteration":184,"passed_time":3.275444935,"remaining_time":14.42966282},
{"learn":[10.94267811],"iteration":185,"passed_time":3.295249798,"remaining_time":14.42114696},
{"learn":[10.94267357],"iteration":186,"passed_time":3.317724811,"remaining_time":14.4241191},
{"learn":[10.94266883],"iteration":187,"passed_time":3.337108551,"remaining_time":14.41346885},
{"learn":[10.94266437],"iteration":188,"passed_time":3.355029655,"remaining_time":14.39645},
{"learn":[10.94265921],"iteration":189,"passed_time":3.373380447,"remaining_time":14.38125348},
{"learn":[10.9426548],"iteration":190,"passed_time":3.388079454,"remaining_time":14.35055643},
{"learn":[10.9426504],"iteration":191,"passed_time":3.402578796,"remaining_time":14.31918577},
{"learn":[10.942646],"iteration":192,"passed_time":3.416935962,"remaining_time":14.28739545},
{"learn":[10.94264159],"iteration":193,"passed_time":3.433131543,"remaining_time":14.2634228},
{"learn":[10.94263715],"iteration":194,"passed_time":3.450233866,"remaining_time":14.24327314},
{"learn":[10.94263269],"iteration":195,"passed_time":3.468383435,"remaining_time":14.22745042},
{"learn":[10.94262749],"iteration":196,"passed_time":3.489251502,"remaining_time":14.22268506},
{"learn":[10.94262306],"iteration":197,"passed_time":3.506010817,"remaining_time":14.20111452},
{"learn":[10.94261864],"iteration":198,"passed_time":3.522154146,"remaining_time":14.17711292},
{"learn":[10.94261422],"iteration":199,"passed_time":3.539015019,"remaining_time":14.15606007},
{"learn":[10.94260982],"iteration":200,"passed_time":3.553868307,"remaining_time":14.12706854},
{"learn":[10.94260531],"iteration":201,"passed_time":3.572145868,"remaining_time":14.11174457},
{"learn":[10.94260091],"iteration":202,"passed_time":3.586534247,"remaining_time":14.08112214},
{"learn":[10.9425965],"iteration":203,"passed_time":3.601840488,"remaining_time":14.05424034},
{"learn":[10.942592],"iteration":204,"passed_time":3.620442519,"remaining_time":14.0402527},
{"learn":[10.94258759],"iteration":205,"passed_time":3.636427999,"remaining_time":14.0161351},
{"learn":[10.94258242],"iteration":206,"passed_time":3.656079877,"remaining_time":14.00614175},
{"learn":[10.94257794],"iteration":207,"passed_time":3.672181422,"remaining_time":13.98253695},
{"learn":[10.94257353],"iteration":208,"passed_time":3.688685837,"remaining_time":13.96052869},
{"learn":[10.94256913],"iteration":209,"passed_time":3.703396268,"remaining_time":13.93182406},
{"learn":[10.94256454],"iteration":210,"passed_time":3.727159709,"remaining_time":13.93710432},
{"learn":[10.94256005],"iteration":211,"passed_time":3.749135993,"remaining_time":13.93546775},
{"learn":[10.94255476],"iteration":212,"passed_time":3.769420328,"remaining_time":13.92738872},
{"learn":[10.94255033],"iteration":213,"passed_time":3.788908013,"remaining_time":13.91626962},
{"learn":[10.94254591],"iteration":214,"passed_time":3.808517483,"remaining_time":13.90551732},
{"learn":[10.94254151],"iteration":215,"passed_time":3.825316945,"remaining_time":13.88448373},
{"learn":[10.9425371],"iteration":216,"passed_time":3.841200607,"remaining_time":13.86018468},
{"learn":[10.94253267],"iteration":217,"passed_time":3.858473128,"remaining_time":13.84094489},
{"learn":[10.94252827],"iteration":218,"passed_time":3.873108133,"remaining_time":13.81231713},
{"learn":[10.94252386],"iteration":219,"passed_time":3.889379913,"remaining_time":13.78961969},
{"learn":[10.94251946],"iteration":220,"passed_time":3.903720107,"remaining_time":13.76017178},
{"learn":[10.94251505],"iteration":221,"passed_time":3.918857053,"remaining_time":13.73365219},
{"learn":[10.94251065],"iteration":222,"passed_time":3.935208914,"remaining_time":13.71146783},
{"learn":[10.9425062],"iteration":223,"passed_time":3.950529484,"remaining_time":13.68576285},
{"learn":[10.94250106],"iteration":224,"passed_time":3.969853258,"remaining_time":13.673939},
{"learn":[10.94249665],"iteration":225,"passed_time":3.984388481,"remaining_time":13.64564905},
{"learn":[10.94249225],"iteration":226,"passed_time":3.99997999,"remaining_time":13.62107723},
{"learn":[10.94248784],"iteration":227,"passed_time":4.014212082,"remaining_time":13.59198126},
{"learn":[10.94248344],"iteration":228,"passed_time":4.028498318,"remaining_time":13.5631974},
{"learn":[10.94247904],"iteration":229,"passed_time":4.042804163,"remaining_time":13.53460524},
{"learn":[10.94247461],"iteration":230,"passed_time":4.058007028,"remaining_time":13.50912296},
{"learn":[10.9424701],"iteration":231,"passed_time":4.079733699,"remaining_time":13.50532535},
{"learn":[10.94246569],"iteration":232,"passed_time":4.094337316,"remaining_time":13.47792584},
{"learn":[10.94246122],"iteration":233,"passed_time":4.111949908,"remaining_time":13.4604856},
{"learn":[10.94245677],"iteration":234,"passed_time":4.128181677,"remaining_time":13.43854886},
{"learn":[10.94245212],"iteration":235,"passed_time":4.149910895,"remaining_time":13.43445731},
{"learn":[10.94244772],"iteration":236,"passed_time":4.164187714,"remaining_time":13.40622458},
{"learn":[10.94244327],"iteration":237,"passed_time":4.181269663,"remaining_time":13.38709027},
{"learn":[10.94243875],"iteration":238,"passed_time":4.200602939,"remaining_time":13.37514158},
{"learn":[10.94243344],"iteration":239,"passed_time":4.221256141,"remaining_time":13.36731111},
{"learn":[10.94242903],"iteration":240,"passed_time":4.237286088,"remaining_time":13.34481386},
{"learn":[10.94242457],"iteration":241,"passed_time":4.256714808,"remaining_time":13.3330158},
{"learn":[10.94242017],"iteration":242,"passed_time":4.274202184,"remaining_time":13.31510721},
{"learn":[10.94241576],"iteration":243,"passed_time":4.289940955,"remaining_time":13.29178427},
{"learn":[10.94241131],"iteration":244,"passed_time":4.308398083,"remaining_time":13.27690021},
{"learn":[10.94240691],"iteration":245,"passed_time":4.324285859,"remaining_time":13.25411194},
{"learn":[10.94240232],"iteration":246,"passed_time":4.341925872,"remaining_time":13.23672138},
{"learn":[10.94239789],"iteration":247,"passed_time":4.361801935,"remaining_time":13.22610909},
{"learn":[10.94239348],"iteration":248,"passed_time":4.37995831,"remaining_time":13.21023571},
{"learn":[10.94238907],"iteration":249,"passed_time":4.400648463,"remaining_time":13.20194539},
{"learn":[10.94238461],"iteration":250,"passed_time":4.419253667,"remaining_time":13.18733465},
{"learn":[10.94237943],"iteration":251,"passed_time":4.442231371,"remaining_time":13.1856709},
{"learn":[10.94237496],"iteration":252,"passed_time":4.465682453,"remaining_time":13.18523633},
{"learn":[10.94237056],"iteration":253,"passed_time":4.481068525,"remaining_time":13.16093354},
{"learn":[10.94236616],"iteration":254,"passed_time":4.495688804,"remaining_time":13.13446337},
{"learn":[10.94236175],"iteration":255,"passed_time":4.511004006,"remaining_time":13.11010539},
{"learn":[10.94235719],"iteration":256,"passed_time":4.528087355,"remaining_time":13.09092959},
{"learn":[10.94235279],"iteration":257,"passed_time":4.542489811,"remaining_time":13.06405984},
{"learn":[10.94234839],"iteration":258,"passed_time":4.557040559,"remaining_time":13.03771063},
{"learn":[10.94234394],"iteration":259,"passed_time":4.57319314,"remaining_time":13.01601124},
{"learn":[10.94233937],"iteration":260,"passed_time":4.594334706,"remaining_time":13.00848026},
{"learn":[10.94233493],"iteration":261,"passed_time":4.609397179,"remaining_time":12.98372183},
{"learn":[10.94233052],"iteration":262,"passed_time":4.62535546,"remaining_time":12.96154743},
{"learn":[10.94232612],"iteration":263,"passed_time":4.639522562,"remaining_time":12.93442654},
{"learn":[10.94232172],"iteration":264,"passed_time":4.654033529,"remaining_time":12.90835715},
{"learn":[10.94231643],"iteration":265,"passed_time":4.670847971,"remaining_time":12.88873087},
{"learn":[10.94231202],"iteration":266,"passed_time":4.685255275,"remaining_time":12.86251729},
{"learn":[10.94230755],"iteration":267,"passed_time":4.705744219,"remaining_time":12.85300287},
{"learn":[10.94230305],"iteration":268,"passed_time":4.722145759,"remaining_time":12.83229944},
{"learn":[10.94229862],"iteration":269,"passed_time":4.737598081,"remaining_time":12.80906148},
{"learn":[10.94229422],"iteration":270,"passed_time":4.752134982,"remaining_time":12.78341846},
{"learn":[10.94228976],"iteration":271,"passed_time":4.767391618,"remaining_time":12.75978345},
{"learn":[10.94228536],"iteration":272,"passed_time":4.783277581,"remaining_time":12.73788572},
{"learn":[10.94228086],"iteration":273,"passed_time":4.804557906,"remaining_time":12.73032496},
{"learn":[10.94227633],"iteration":274,"passed_time":4.822083604,"remaining_time":12.71276586},
{"learn":[10.94227192],"iteration":275,"passed_time":4.836480157,"remaining_time":12.68699867},
{"learn":[10.94226752],"iteration":276,"passed_time":4.853182117,"remaining_time":12.66733094},
{"learn":[10.94226311],"iteration":277,"passed_time":4.867592238,"remaining_time":12.64173236},
{"learn":[10.94225871],"iteration":278,"passed_time":4.881579528,"remaining_time":12.61512129},
{"learn":[10.94225416],"iteration":279,"passed_time":4.900347303,"remaining_time":12.60089306},
{"learn":[10.9422497],"iteration":280,"passed_time":4.915627179,"remaining_time":12.57770798},
{"learn":[10.9422453],"iteration":281,"passed_time":4.931984437,"remaining_time":12.55732208},
{"learn":[10.94224078],"iteration":282,"passed_time":4.950868058,"remaining_time":12.54336536},
{"learn":[10.942236],"iteration":283,"passed_time":4.972866645,"remaining_time":12.53722718},
{"learn":[10.9422316],"iteration":284,"passed_time":4.989134343,"remaining_time":12.51660019},
{"learn":[10.9422272],"iteration":285,"passed_time":5.003359078,"remaining_time":12.49090343},
{"learn":[10.94222265],"iteration":286,"passed_time":5.020585788,"remaining_time":12.47274448},
{"learn":[10.94221745],"iteration":287,"passed_time":5.042761472,"remaining_time":12.46682697},
{"learn":[10.94221304],"iteration":288,"passed_time":5.057662304,"remaining_time":12.4428993},
{"learn":[10.94220864],"iteration":289,"passed_time":5.073364378,"remaining_time":12.42099555},
{"learn":[10.94220424],"iteration":290,"passed_time":5.088841746,"remaining_time":12.39858693},
{"learn":[10.94219983],"iteration":291,"passed_time":5.103125309,"remaining_time":12.37333123},
{"learn":[10.94219467],"iteration":292,"passed_time":5.121732923,"remaining_time":12.35858422},
{"learn":[10.94219027],"iteration":293,"passed_time":5.13728295,"remaining_time":12.33646858},
{"learn":[10.94218586],"iteration":294,"passed_time":5.15188689,"remaining_time":12.31213647},
{"learn":[10.94218146],"iteration":295,"passed_time":5.166282007,"remaining_time":12.28737342},
{"learn":[10.94217706],"iteration":296,"passed_time":5.180493469,"remaining_time":12.26224548},
{"learn":[10.94217265],"iteration":297,"passed_time":5.195897396,"remaining_time":12.23999991},
{"learn":[10.94216738],"iteration":298,"passed_time":5.216796855,"remaining_time":12.23068427},
{"learn":[10.94216274],"iteration":299,"passed_time":5.235087215,"remaining_time":12.2152035},
{"learn":[10.94215834],"iteration":300,"passed_time":5.25171674,"remaining_time":12.19584718},
{"learn":[10.94215298],"iteration":301,"passed_time":5.27505987,"remaining_time":12.19202579},
{"learn":[10.94214853],"iteration":302,"passed_time":5.29732637,"remaining_time":12.18559894},
{"learn":[10.9421441],"iteration":303,"passed_time":5.315230715,"remaining_time":12.16908085},
{"learn":[10.94213953],"iteration":304,"passed_time":5.338276434,"remaining_time":12.16426925},
{"learn":[10.94213513],"iteration":305,"passed_time":5.355799004,"remaining_time":12.14681212},
{"learn":[10.94213072],"iteration":306,"passed_time":5.375670425,"remaining_time":12.13465669},
{"learn":[10.94212631],"iteration":307,"passed_time":5.391534499,"remaining_time":12.11344764},
{"learn":[10.94212184],"iteration":308,"passed_time":5.408443601,"remaining_time":12.09461012},
{"learn":[10.94211722],"iteration":309,"passed_time":5.427445404,"remaining_time":12.080443},
{"learn":[10.94211254],"iteration":310,"passed_time":5.45257905,"remaining_time":12.07982947},
{"learn":[10.94210814],"iteration":311,"passed_time":5.470324545,"remaining_time":12.06276695},
{"learn":[10.94210374],"iteration":312,"passed_time":5.486352913,"remaining_time":12.04193115},
{"learn":[10.94209932],"iteration":313,"passed_time":5.503490699,"remaining_time":12.02354974},
{"learn":[10.94209492],"iteration":314,"passed_time":5.518962976,"remaining_time":12.00155441},
{"learn":[10.94209051],"iteration":315,"passed_time":5.534466258,"remaining_time":11.97966747},
{"learn":[10.94208601],"iteration":316,"passed_time":5.555665361,"remaining_time":11.97009288},
{"learn":[10.94208156],"iteration":317,"passed_time":5.572603984,"remaining_time":11.95130791},
{"learn":[10.94207714],"iteration":318,"passed_time":5.589096491,"remaining_time":11.93158216},
{"learn":[10.94207271],"iteration":319,"passed_time":5.605327762,"remaining_time":11.91132149},
{"learn":[10.9420683],"iteration":320,"passed_time":5.619683364,"remaining_time":11.88711839},
{"learn":[10.9420639],"iteration":321,"passed_time":5.633855577,"remaining_time":11.86259031},
{"learn":[10.94205929],"iteration":322,"passed_time":5.653396199,"remaining_time":11.84937841},
{"learn":[10.94205487],"iteration":323,"passed_time":5.668959646,"remaining_time":11.82782938},
{"learn":[10.94204915],"iteration":324,"passed_time":5.685125596,"remaining_time":11.80756854},
{"learn":[10.94204475],"iteration":325,"passed_time":5.699562925,"remaining_time":11.78375893},
{"learn":[10.94204031],"iteration":326,"passed_time":5.715313702,"remaining_time":11.76270985},
{"learn":[10.94203447],"iteration":327,"passed_time":5.734258698,"remaining_time":11.74823733},
{"learn":[10.94203006],"iteration":328,"passed_time":5.751505655,"remaining_time":11.73027445},
{"learn":[10.94202546],"iteration":329,"passed_time":5.770773515,"remaining_time":11.71641895},
{"learn":[10.94202092],"iteration":330,"passed_time":5.788305766,"remaining_time":11.69902283},
{"learn":[10.94201632],"iteration":331,"passed_time":5.80988041,"remaining_time":11.68975938},
{"learn":[10.94201186],"iteration":332,"passed_time":5.826687932,"remaining_time":11.67087343},
{"learn":[10.94200746],"iteration":333,"passed_time":5.842259549,"remaining_time":11.64953551},
{"learn":[10.94200305],"iteration":334,"passed_time":5.858426571,"remaining_time":11.62941394},
{"learn":[10.94199865],"iteration":335,"passed_time":5.876001308,"remaining_time":11.61209782},
{"learn":[10.94199425],"iteration":336,"passed_time":5.891793466,"remaining_time":11.5912732},
{"learn":[10.94198984],"iteration":337,"passed_time":5.907806873,"remaining_time":11.57091169},
{"learn":[10.9419853],"iteration":338,"passed_time":5.925965554,"remaining_time":11.55475879},
{"learn":[10.9419809],"iteration":339,"passed_time":5.941787241,"remaining_time":11.53405759},
{"learn":[10.94197643],"iteration":340,"passed_time":5.958708602,"remaining_time":11.51551017},
{"learn":[10.94197202],"iteration":341,"passed_time":5.976212824,"remaining_time":11.49809368},
{"learn":[10.9419674],"iteration":342,"passed_time":5.997099811,"remaining_time":11.4871562},
{"learn":[10.94196299],"iteration":343,"passed_time":6.013403783,"remaining_time":11.46742117},
{"learn":[10.94195787],"iteration":344,"passed_time":6.031730742,"remaining_time":11.45154677},
{"learn":[10.94195346],"iteration":345,"passed_time":6.046883318,"remaining_time":11.42965806},
{"learn":[10.94194906],"iteration":346,"passed_time":6.061725339,"remaining_time":11.40722376},
{"learn":[10.94194452],"iteration":347,"passed_time":6.080910735,"remaining_time":11.39297069},
{"learn":[10.94193864],"iteration":348,"passed_time":6.09808813,"remaining_time":11.37494376},
{"learn":[10.94193424],"iteration":349,"passed_time":6.112464352,"remaining_time":11.35171951},
{"learn":[10.94192984],"iteration":350,"passed_time":6.126922185,"remaining_time":11.32869658},
{"learn":[10.94192395],"iteration":351,"passed_time":6.143746991,"remaining_time":11.31007969},
{"learn":[10.94191884],"iteration":352,"passed_time":6.160683341,"remaining_time":11.2916774},
{"learn":[10.94191444],"iteration":353,"passed_time":6.174978367,"remaining_time":11.26846335},
{"learn":[10.94191003],"iteration":354,"passed_time":6.190999263,"remaining_time":11.24843528},
{"learn":[10.94190563],"iteration":355,"passed_time":6.206254426,"remaining_time":11.22704452},
{"learn":[10.94190122],"iteration":356,"passed_time":6.220878237,"remaining_time":11.204551},
{"learn":[10.94189682],"iteration":357,"passed_time":6.23540415,"remaining_time":11.18192588},
{"learn":[10.94189235],"iteration":358,"passed_time":6.255032157,"remaining_time":11.16845574},
{"learn":[10.94188794],"iteration":359,"passed_time":6.273833454,"remaining_time":11.1534817},
{"learn":[10.94188353],"iteration":360,"passed_time":6.292357848,"remaining_time":11.1379963},
{"learn":[10.94187913],"iteration":361,"passed_time":6.307673547,"remaining_time":11.11683901},
{"learn":[10.94187473],"iteration":362,"passed_time":6.322455302,"remaining_time":11.09477694},
{"learn":[10.94187033],"iteration":363,"passed_time":6.336687415,"remaining_time":11.07179449},
{"learn":[10.9418646],"iteration":364,"passed_time":6.355294265,"remaining_time":11.05647084},
{"learn":[10.9418602],"iteration":365,"passed_time":6.369873189,"remaining_time":11.03415192},
{"learn":[10.94185561],"iteration":366,"passed_time":6.385990803,"remaining_time":11.0145291},
{"learn":[10.9418512],"iteration":367,"passed_time":6.401953863,"remaining_time":10.9946599},
{"learn":[10.9418468],"iteration":368,"passed_time":6.417120665,"remaining_time":10.97345024},
{"learn":[10.9418424],"iteration":369,"passed_time":6.433821859,"remaining_time":10.95488587},
{"learn":[10.94183799],"iteration":370,"passed_time":6.448999903,"remaining_time":10.93374916},
{"learn":[10.94183355],"iteration":371,"passed_time":6.466605099,"remaining_time":10.91674194},
{"learn":[10.94182915],"iteration":372,"passed_time":6.481568373,"remaining_time":10.89529054},
{"learn":[10.94182456],"iteration":373,"passed_time":6.502055487,"remaining_time":10.88311961},
{"learn":[10.94182014],"iteration":374,"passed_time":6.517595906,"remaining_time":10.86265984},
{"learn":[10.94181569],"iteration":375,"passed_time":6.534420556,"remaining_time":10.84435752},
{"learn":[10.94181129],"iteration":376,"passed_time":6.548883341,"remaining_time":10.82216},
{"learn":[10.9418068],"iteration":377,"passed_time":6.566532504,"remaining_time":10.80524661},
{"learn":[10.9418024],"iteration":378,"passed_time":6.581887538,"remaining_time":10.78457035},
{"learn":[10.941798],"iteration":379,"passed_time":6.596150675,"remaining_time":10.76214058},
{"learn":[10.94179359],"iteration":380,"passed_time":6.613064584,"remaining_time":10.74406031},
{"learn":[10.94178914],"iteration":381,"passed_time":6.628504629,"remaining_time":10.72360173},
{"learn":[10.94178455],"iteration":382,"passed_time":6.651113941,"remaining_time":10.7147188},
{"learn":[10.94178015],"iteration":383,"passed_time":6.665896999,"remaining_time":10.69320977},
{"learn":[10.94177575],"iteration":384,"passed_time":6.682736157,"remaining_time":10.6750201},
{"learn":[10.94177135],"iteration":385,"passed_time":6.697036006,"remaining_time":10.65279821},
{"learn":[10.94176688],"iteration":386,"passed_time":6.712544562,"remaining_time":10.63253183},
{"learn":[10.94176235],"iteration":387,"passed_time":6.729913215,"remaining_time":10.61522394},
{"learn":[10.94175795],"iteration":388,"passed_time":6.744820655,"remaining_time":10.59404992},
{"learn":[10.94175355],"iteration":389,"passed_time":6.760504678,"remaining_time":10.5741227},
{"learn":[10.94174914],"iteration":390,"passed_time":6.774979838,"remaining_time":10.55233433},
{"learn":[10.94174474],"iteration":391,"passed_time":6.789070847,"remaining_time":10.52998744},
{"learn":[10.94174034],"iteration":392,"passed_time":6.803549146,"remaining_time":10.50828074},
{"learn":[10.94173588],"iteration":393,"passed_time":6.819325768,"remaining_time":10.48860765},
{"learn":[10.94173147],"iteration":394,"passed_time":6.833850495,"remaining_time":10.46703683},
{"learn":[10.94172695],"iteration":395,"passed_time":6.849780772,"remaining_time":10.44764542},
{"learn":[10.94172254],"iteration":396,"passed_time":6.865910715,"remaining_time":10.42857471},
{"learn":[10.94171812],"iteration":397,"passed_time":6.882042635,"remaining_time":10.40952177},
{"learn":[10.94171354],"iteration":398,"passed_time":6.903019138,"remaining_time":10.39778071},
{"learn":[10.94170901],"iteration":399,"passed_time":6.923235961,"remaining_time":10.38485394},
{"learn":[10.9417046],"iteration":400,"passed_time":6.939453852,"remaining_time":10.36591735},
{"learn":[10.94170013],"iteration":401,"passed_time":6.954918856,"remaining_time":10.34587432},
{"learn":[10.94169573],"iteration":402,"passed_time":6.969388355,"remaining_time":10.32437928},
{"learn":[10.94169132],"iteration":403,"passed_time":6.983570712,"remaining_time":10.30249541},
{"learn":[10.9416868],"iteration":404,"passed_time":7.000796664,"remaining_time":10.28512103},
{"learn":[10.94168221],"iteration":405,"passed_time":7.021029996,"remaining_time":10.27214733},
{"learn":[10.94167781],"iteration":406,"passed_time":7.035507677,"remaining_time":10.25075197},
{"learn":[10.94167341],"iteration":407,"passed_time":7.049926711,"remaining_time":10.22930542},
{"learn":[10.94166897],"iteration":408,"passed_time":7.066105471,"remaining_time":10.21043602},
{"learn":[10.94166451],"iteration":409,"passed_time":7.081330077,"remaining_time":10.1902067},
{"learn":[10.94166011],"iteration":410,"passed_time":7.095774162,"remaining_time":10.16888317},
{"learn":[10.9416549],"iteration":411,"passed_time":7.113465041,"remaining_time":10.15222681},
{"learn":[10.9416505],"iteration":412,"passed_time":7.127906642,"remaining_time":10.13094721},
{"learn":[10.9416461],"iteration":413,"passed_time":7.142053696,"remaining_time":10.10928373},
{"learn":[10.94164169],"iteration":414,"passed_time":7.158187143,"remaining_time":10.09045658},
{"learn":[10.94163596],"iteration":415,"passed_time":7.175020768,"remaining_time":10.07262531},
{"learn":[10.94163155],"iteration":416,"passed_time":7.189405723,"remaining_time":10.05137539},
{"learn":[10.94162715],"iteration":417,"passed_time":7.203868853,"remaining_time":10.03026716},
{"learn":[10.94162275],"iteration":418,"passed_time":7.218453167,"remaining_time":10.00935869},
{"learn":[10.94161824],"iteration":419,"passed_time":7.236718646,"remaining_time":9.993563844},
{"learn":[10.94161384],"iteration":420,"passed_time":7.252070315,"remaining_time":9.973749911},
{"learn":[10.94160943],"iteration":421,"passed_time":7.270123307,"remaining_time":9.957657041},
{"learn":[10.94160503],"iteration":422,"passed_time":7.28895827,"remaining_time":9.942621565},
{"learn":[10.94160062],"iteration":423,"passed_time":7.31246986,"remaining_time":9.933921319},
{"learn":[10.94159621],"iteration":424,"passed_time":7.330985132,"remaining_time":9.918391649},
{"learn":[10.9415916],"iteration":425,"passed_time":7.353862727,"remaining_time":9.908725834},
{"learn":[10.94158571],"iteration":426,"passed_time":7.382206833,"remaining_time":9.90633376},
{"learn":[10.94158131],"iteration":427,"passed_time":7.401661849,"remaining_time":9.891940602},
{"learn":[10.94157691],"iteration":428,"passed_time":7.421625104,"remaining_time":9.878200313},
{"learn":[10.9415725],"iteration":429,"passed_time":7.443096455,"remaining_time":9.866430184},
{"learn":[10.94156808],"iteration":430,"passed_time":7.463477493,"remaining_time":9.853175623},
{"learn":[10.94156367],"iteration":431,"passed_time":7.483532409,"remaining_time":9.839459279},
{"learn":[10.9415585],"iteration":432,"passed_time":7.504296663,"remaining_time":9.826642512},
{"learn":[10.9415541],"iteration":433,"passed_time":7.523234761,"remaining_time":9.811407546},
{"learn":[10.94154969],"iteration":434,"passed_time":7.542305094,"remaining_time":9.796327306},
{"learn":[10.94154529],"iteration":435,"passed_time":7.561656753,"remaining_time":9.78159268},
{"learn":[10.94154081],"iteration":436,"passed_time":7.58442079,"remaining_time":9.771233192},
{"learn":[10.94153641],"iteration":437,"passed_time":7.603089531,"remaining_time":9.755562366},
{"learn":[10.94153201],"iteration":438,"passed_time":7.623000969,"remaining_time":9.741465931},
{"learn":[10.9415276],"iteration":439,"passed_time":7.639518142,"remaining_time":9.72302309},
{"learn":[10.9415232],"iteration":440,"passed_time":7.655044539,"remaining_time":9.7033331},
{"learn":[10.9415185],"iteration":441,"passed_time":7.674759373,"remaining_time":9.688949616},
{"learn":[10.94151387],"iteration":442,"passed_time":7.691730162,"remaining_time":9.671091874},
{"learn":[10.9415093],"iteration":443,"passed_time":7.712679925,"remaining_time":9.658220807},
{"learn":[10.9415049],"iteration":444,"passed_time":7.727226609,"remaining_time":9.637327569},
{"learn":[10.9415005],"iteration":445,"passed_time":7.741799305,"remaining_time":9.6164951},
{"learn":[10.94149606],"iteration":446,"passed_time":7.758160985,"remaining_time":9.597903858},
{"learn":[10.94149166],"iteration":447,"passed_time":7.77259463,"remaining_time":9.576946955},
{"learn":[10.94148716],"iteration":448,"passed_time":7.788454046,"remaining_time":9.557768774},
{"learn":[10.94148274],"iteration":449,"passed_time":7.805205247,"remaining_time":9.539695301},
{"learn":[10.94147815],"iteration":450,"passed_time":7.824300953,"remaining_time":9.524481648},
{"learn":[10.94147374],"iteration":451,"passed_time":7.838928184,"remaining_time":9.503833285},
{"learn":[10.94146934],"iteration":452,"passed_time":7.853242439,"remaining_time":9.482833585},
{"learn":[10.94146494],"iteration":453,"passed_time":7.86830978,"remaining_time":9.462769031},
{"learn":[10.94146054],"iteration":454,"passed_time":7.884277833,"remaining_time":9.443805317},
{"learn":[10.94145546],"iteration":455,"passed_time":7.900108887,"remaining_time":9.424691303},
{"learn":[10.94145099],"iteration":456,"passed_time":7.916456399,"remaining_time":9.406205305},
{"learn":[10.94144578],"iteration":457,"passed_time":7.932094759,"remaining_time":9.38688943},
{"learn":[10.94144138],"iteration":458,"passed_time":7.948101148,"remaining_time":9.368023358},
{"learn":[10.94143688],"iteration":459,"passed_time":7.97074266,"remaining_time":9.356958774},
{"learn":[10.94143235],"iteration":460,"passed_time":7.986633821,"remaining_time":9.337951474},
{"learn":[10.94142795],"iteration":461,"passed_time":8.003287685,"remaining_time":9.319845832},
{"learn":[10.9414234],"iteration":462,"passed_time":8.021943257,"remaining_time":9.304068097},
{"learn":[10.941419],"iteration":463,"passed_time":8.037614564,"remaining_time":9.284830617},
{"learn":[10.94141459],"iteration":464,"passed_time":8.059204238,"remaining_time":9.272417779},
{"learn":[10.94141019],"iteration":465,"passed_time":8.073439615,"remaining_time":9.251538099},
{"learn":[10.94140578],"iteration":466,"passed_time":8.087740965,"remaining_time":9.230762173},
{"learn":[10.94140137],"iteration":467,"passed_time":8.103210233,"remaining_time":9.211341546},
{"learn":[10.9413969],"iteration":468,"passed_time":8.120145327,"remaining_time":9.193597374},
{"learn":[10.9413925],"iteration":469,"passed_time":8.134526427,"remaining_time":9.172976609},
{"learn":[10.94138744],"iteration":470,"passed_time":8.150242527,"remaining_time":9.153881734},
{"learn":[10.94138304],"iteration":471,"passed_time":8.164673129,"remaining_time":9.133363161},
{"learn":[10.94137856],"iteration":472,"passed_time":8.187646015,"remaining_time":9.122387844},
{"learn":[10.94137416],"iteration":473,"passed_time":8.202346048,"remaining_time":9.102181479},
{"learn":[10.94136973],"iteration":474,"passed_time":8.217451725,"remaining_time":9.082446644},
{"learn":[10.9413653],"iteration":475,"passed_time":8.233379826,"remaining_time":9.063636615},
{"learn":[10.9413609],"iteration":476,"passed_time":8.248025073,"remaining_time":9.043432103},
{"learn":[10.94135645],"iteration":477,"passed_time":8.268510498,"remaining_time":9.029628619},
{"learn":[10.94135204],"iteration":478,"passed_time":8.287572023,"remaining_time":9.014248485},
{"learn":[10.94134764],"iteration":479,"passed_time":8.305469249,"remaining_time":8.997591686},
{"learn":[10.94134318],"iteration":480,"passed_time":8.325227069,"remaining_time":8.982937316},
{"learn":[10.94133859],"iteration":481,"passed_time":8.347937176,"remaining_time":8.971434558},
{"learn":[10.94133419],"iteration":482,"passed_time":8.367761744,"remaining_time":8.956796732},
{"learn":[10.94132979],"iteration":483,"passed_time":8.386813812,"remaining_time":8.941313899},
{"learn":[10.94132538],"iteration":484,"passed_time":8.410637162,"remaining_time":8.93088276},
{"learn":[10.94132097],"iteration":485,"passed_time":8.431469344,"remaining_time":8.91723301},
{"learn":[10.94131621],"iteration":486,"passed_time":8.456796339,"remaining_time":8.908288546},
{"learn":[10.94131108],"iteration":487,"passed_time":8.479376981,"remaining_time":8.896395521},
{"learn":[10.94130647],"iteration":488,"passed_time":8.500789346,"remaining_time":8.883237946},
{"learn":[10.94130207],"iteration":489,"passed_time":8.519408187,"remaining_time":8.867139134},
{"learn":[10.94129764],"iteration":490,"passed_time":8.540184405,"remaining_time":8.853266521},
{"learn":[10.94129321],"iteration":491,"passed_time":8.560467777,"remaining_time":8.838856973},
{"learn":[10.94128881],"iteration":492,"passed_time":8.579808335,"remaining_time":8.823454008},
{"learn":[10.94128352],"iteration":493,"passed_time":8.608161996,"remaining_time":8.817267146},
{"learn":[10.94127886],"iteration":494,"passed_time":8.636194314,"remaining_time":8.810662886},
{"learn":[10.94127445],"iteration":495,"passed_time":8.653111789,"remaining_time":8.792678108},
{"learn":[10.94127005],"iteration":496,"passed_time":8.669521673,"remaining_time":8.774183906},
{"learn":[10.94126565],"iteration":497,"passed_time":8.684591146,"remaining_time":8.754346899},
{"learn":[10.94126116],"iteration":498,"passed_time":8.701416881,"remaining_time":8.7362923},
{"learn":[10.94125671],"iteration":499,"passed_time":8.717411983,"remaining_time":8.717411983},
{"learn":[10.94125224],"iteration":500,"passed_time":8.734238616,"remaining_time":8.699371396},
{"learn":[10.94124771],"iteration":501,"passed_time":8.752715192,"remaining_time":8.682972442},
{"learn":[10.94124316],"iteration":502,"passed_time":8.77321913,"remaining_time":8.668568405},
{"learn":[10.9412387],"iteration":503,"passed_time":8.788353777,"remaining_time":8.648856098},
{"learn":[10.94123427],"iteration":504,"passed_time":8.806843137,"remaining_time":8.632450203},
{"learn":[10.94122986],"iteration":505,"passed_time":8.823035209,"remaining_time":8.613793267},
{"learn":[10.94122527],"iteration":506,"passed_time":8.8430302,"remaining_time":8.598843962},
{"learn":[10.9412208],"iteration":507,"passed_time":8.862380125,"remaining_time":8.583250043},
{"learn":[10.94121627],"iteration":508,"passed_time":8.880741448,"remaining_time":8.566687723},
{"learn":[10.94121186],"iteration":509,"passed_time":8.898184666,"remaining_time":8.549236247},
{"learn":[10.94120745],"iteration":510,"passed_time":8.913102361,"remaining_time":8.529368013},
{"learn":[10.94120296],"iteration":511,"passed_time":8.933442787,"remaining_time":8.514687657},
{"learn":[10.94119855],"iteration":512,"passed_time":8.947804112,"remaining_time":8.494309167},
{"learn":[10.94119415],"iteration":513,"passed_time":8.964980197,"remaining_time":8.476615517},
{"learn":[10.94118975],"iteration":514,"passed_time":8.98241485,"remaining_time":8.459167383},
{"learn":[10.94118527],"iteration":515,"passed_time":8.998838807,"remaining_time":8.440771284},
{"learn":[10.94118087],"iteration":516,"passed_time":9.013722477,"remaining_time":8.420943823},
{"learn":[10.94117641],"iteration":517,"passed_time":9.028876062,"remaining_time":8.401386606},
{"learn":[10.94117201],"iteration":518,"passed_time":9.043245201,"remaining_time":8.381119348},
{"learn":[10.94116758],"iteration":519,"passed_time":9.058502108,"remaining_time":8.361694253},
{"learn":[10.94116296],"iteration":520,"passed_time":9.076958128,"remaining_time":8.345226379},
{"learn":[10.94115855],"iteration":521,"passed_time":9.091344778,"remaining_time":8.325024529},
{"learn":[10.94115408],"iteration":522,"passed_time":9.108293026,"remaining_time":8.307181212},
{"learn":[10.94114967],"iteration":523,"passed_time":9.123506857,"remaining_time":8.287765771},
{"learn":[10.94114508],"iteration":524,"passed_time":9.144077605,"remaining_time":8.273213071},
{"learn":[10.94114043],"iteration":525,"passed_time":9.16300783,"remaining_time":8.257159147},
{"learn":[10.94113581],"iteration":526,"passed_time":9.179967875,"remaining_time":8.239326005},
{"learn":[10.94113129],"iteration":527,"passed_time":9.19652802,"remaining_time":8.221138685},
{"learn":[10.94112688],"iteration":528,"passed_time":9.212183869,"remaining_time":8.202152367},
{"learn":[10.94112248],"iteration":529,"passed_time":9.227109872,"remaining_time":8.182531396},
{"learn":[10.94111808],"iteration":530,"passed_time":9.241910136,"remaining_time":8.16281705},
{"learn":[10.94111368],"iteration":531,"passed_time":9.256429181,"remaining_time":8.14287379},
{"learn":[10.94110925],"iteration":532,"passed_time":9.274394094,"remaining_time":8.125970059},
{"learn":[10.94110485],"iteration":533,"passed_time":9.291998435,"remaining_time":8.108747698},
{"learn":[10.94110045],"iteration":534,"passed_time":9.308133991,"remaining_time":8.090247301},
{"learn":[10.94109605],"iteration":535,"passed_time":9.325019818,"remaining_time":8.072405215},
{"learn":[10.94109165],"iteration":536,"passed_time":9.339887817,"remaining_time":8.052826926},
{"learn":[10.94108719],"iteration":537,"passed_time":9.358872668,"remaining_time":8.036801436},
{"learn":[10.94108274],"iteration":538,"passed_time":9.374615516,"remaining_time":8.017992121},
{"learn":[10.94107834],"iteration":539,"passed_time":9.390175053,"remaining_time":7.999038008},
{"learn":[10.94107393],"iteration":540,"passed_time":9.404935585,"remaining_time":7.979418547},
{"learn":[10.94106953],"iteration":541,"passed_time":9.419200608,"remaining_time":7.9593983},
{"learn":[10.94106513],"iteration":542,"passed_time":9.433899815,"remaining_time":7.93976467},
{"learn":[10.94106073],"iteration":543,"passed_time":9.448229531,"remaining_time":7.91983946},
{"learn":[10.94105633],"iteration":544,"passed_time":9.462606879,"remaining_time":7.89997455},
{"learn":[10.94105186],"iteration":545,"passed_time":9.481934273,"remaining_time":7.884245714},
{"learn":[10.94104746],"iteration":546,"passed_time":9.497548348,"remaining_time":7.865428523},
{"learn":[10.94104304],"iteration":547,"passed_time":9.513372056,"remaining_time":7.846795929},
{"learn":[10.94103839],"iteration":548,"passed_time":9.534132194,"remaining_time":7.832228815},
{"learn":[10.94103399],"iteration":549,"passed_time":9.548474021,"remaining_time":7.812387835},
{"learn":[10.94102955],"iteration":550,"passed_time":9.564154964,"remaining_time":7.793658038},
{"learn":[10.94102512],"iteration":551,"passed_time":9.580573521,"remaining_time":7.77553793},
{"learn":[10.94102072],"iteration":552,"passed_time":9.595266286,"remaining_time":7.756028987},
{"learn":[10.94101626],"iteration":553,"passed_time":9.610784969,"remaining_time":7.737202339},
{"learn":[10.94101186],"iteration":554,"passed_time":9.625173227,"remaining_time":7.717481236},
{"learn":[10.94100728],"iteration":555,"passed_time":9.645584155,"remaining_time":7.702588785},
{"learn":[10.94100279],"iteration":556,"passed_time":9.662045101,"remaining_time":7.684534972},
{"learn":[10.94099839],"iteration":557,"passed_time":9.676432549,"remaining_time":7.664844421},
{"learn":[10.94099398],"iteration":558,"passed_time":9.69088152,"remaining_time":7.645221378},
{"learn":[10.94098953],"iteration":559,"passed_time":9.707149283,"remaining_time":7.627045865},
{"learn":[10.94098513],"iteration":560,"passed_time":9.721482511,"remaining_time":7.607363319},
{"learn":[10.9409806],"iteration":561,"passed_time":9.739122506,"remaining_time":7.590276971},
{"learn":[10.94097545],"iteration":562,"passed_time":9.754443396,"remaining_time":7.571388568},
{"learn":[10.94097089],"iteration":563,"passed_time":9.770401662,"remaining_time":7.55300554},
{"learn":[10.94096649],"iteration":564,"passed_time":9.784898515,"remaining_time":7.533505936},
{"learn":[10.94096209],"iteration":565,"passed_time":9.799575223,"remaining_time":7.51416192},
{"learn":[10.94095769],"iteration":566,"passed_time":9.814470036,"remaining_time":7.495000927},
{"learn":[10.94095326],"iteration":567,"passed_time":9.829914468,"remaining_time":7.476272976},
{"learn":[10.94094811],"iteration":568,"passed_time":9.850938335,"remaining_time":7.461782816},
{"learn":[10.94094351],"iteration":569,"passed_time":9.868562482,"remaining_time":7.44470503},
{"learn":[10.94093829],"iteration":570,"passed_time":9.88665972,"remaining_time":7.42798077},
{"learn":[10.94093388],"iteration":571,"passed_time":9.902465696,"remaining_time":7.409537269},
{"learn":[10.94092948],"iteration":572,"passed_time":9.918402908,"remaining_time":7.391200771},
{"learn":[10.94092505],"iteration":573,"passed_time":9.934350269,"remaining_time":7.372880164},
{"learn":[10.94092061],"iteration":574,"passed_time":9.949956572,"remaining_time":7.354315727},
{"learn":[10.94091615],"iteration":575,"passed_time":9.965328226,"remaining_time":7.335588833},
{"learn":[10.94091172],"iteration":576,"passed_time":9.981372678,"remaining_time":7.317366799},
{"learn":[10.94090727],"iteration":577,"passed_time":9.997033781,"remaining_time":7.298872415},
{"learn":[10.94090286],"iteration":578,"passed_time":10.01137354,"remaining_time":7.279427049},
{"learn":[10.94089841],"iteration":579,"passed_time":10.03235686,"remaining_time":7.264810143},
{"learn":[10.94089401],"iteration":580,"passed_time":10.05085775,"remaining_time":7.248381063},
{"learn":[10.9408895],"iteration":581,"passed_time":10.07769299,"remaining_time":7.237930703},
{"learn":[10.94088503],"iteration":582,"passed_time":10.10101591,"remaining_time":7.224911894},
{"learn":[10.94088058],"iteration":583,"passed_time":10.11923061,"remaining_time":7.208219062},
{"learn":[10.94087613],"iteration":584,"passed_time":10.13570269,"remaining_time":7.190284816},
{"learn":[10.94087172],"iteration":585,"passed_time":10.15198298,"remaining_time":7.172220058},
{"learn":[10.94086708],"iteration":586,"passed_time":10.17679121,"remaining_time":7.160161448},
{"learn":[10.94086262],"iteration":587,"passed_time":10.1930363,"remaining_time":7.142059448},
{"learn":[10.94085818],"iteration":588,"passed_time":10.20957878,"remaining_time":7.124171271},
{"learn":[10.94085378],"iteration":589,"passed_time":10.22533041,"remaining_time":7.105738079},
{"learn":[10.94084937],"iteration":590,"passed_time":10.24170419,"remaining_time":7.087744521},
{"learn":[10.94084497],"iteration":591,"passed_time":10.25658234,"remaining_time":7.068725666},
{"learn":[10.94084054],"iteration":592,"passed_time":10.27617501,"remaining_time":7.052956543},
{"learn":[10.94083614],"iteration":593,"passed_time":10.29428143,"remaining_time":7.036158687},
{"learn":[10.94083161],"iteration":594,"passed_time":10.31665214,"remaining_time":7.022259022},
{"learn":[10.94082719],"iteration":595,"passed_time":10.33567734,"remaining_time":7.006063163},
{"learn":[10.94082278],"iteration":596,"passed_time":10.35753016,"remaining_time":6.991766593},
{"learn":[10.94081827],"iteration":597,"passed_time":10.37532002,"remaining_time":6.974713459},
{"learn":[10.94081372],"iteration":598,"passed_time":10.39632637,"remaining_time":6.959811145},
{"learn":[10.94080932],"iteration":599,"passed_time":10.41179297,"remaining_time":6.941195311},
{"learn":[10.94080479],"iteration":600,"passed_time":10.43355079,"remaining_time":6.926766667},
{"learn":[10.94079961],"iteration":601,"passed_time":10.45363441,"remaining_time":6.911206803},
{"learn":[10.9407952],"iteration":602,"passed_time":10.4695069,"remaining_time":6.892859435},
{"learn":[10.9407908],"iteration":603,"passed_time":10.48545907,"remaining_time":6.874572505},
{"learn":[10.9407864],"iteration":604,"passed_time":10.50217287,"remaining_time":6.856790551},
{"learn":[10.94078125],"iteration":605,"passed_time":10.52040329,"remaining_time":6.839998179},
{"learn":[10.94077678],"iteration":606,"passed_time":10.53903253,"remaining_time":6.823459282},
{"learn":[10.94077238],"iteration":607,"passed_time":10.55442742,"remaining_time":6.804828208},
{"learn":[10.94076793],"iteration":608,"passed_time":10.57053655,"remaining_time":6.786666321},
{"learn":[10.94076346],"iteration":609,"passed_time":10.58697902,"remaining_time":6.768724294},
{"learn":[10.94075906],"iteration":610,"passed_time":10.60208503,"remaining_time":6.749936294},
{"learn":[10.94075451],"iteration":611,"passed_time":10.62127451,"remaining_time":6.733749199},
{"learn":[10.94075003],"iteration":612,"passed_time":10.63831752,"remaining_time":6.716197196},
{"learn":[10.94074563],"iteration":613,"passed_time":10.65405618,"remaining_time":6.697826851},
{"learn":[10.94074055],"iteration":614,"passed_time":10.67611817,"remaining_time":6.683423567},
{"learn":[10.94073599],"iteration":615,"passed_time":10.69332718,"remaining_time":6.665970188},
{"learn":[10.94073159],"iteration":616,"passed_time":10.71251404,"remaining_time":6.649745344},
{"learn":[10.94072698],"iteration":617,"passed_time":10.73682441,"remaining_time":6.636677872},
{"learn":[10.94072257],"iteration":618,"passed_time":10.7541459,"remaining_time":6.619272353},
{"learn":[10.9407181],"iteration":619,"passed_time":10.77318547,"remaining_time":6.602920129},
{"learn":[10.94071356],"iteration":620,"passed_time":10.79117168,"remaining_time":6.585916371},
{"learn":[10.94070911],"iteration":621,"passed_time":10.80831358,"remaining_time":6.568396357},
{"learn":[10.94070462],"iteration":622,"passed_time":10.82552192,"remaining_time":6.550917757},
{"learn":[10.94070011],"iteration":623,"passed_time":10.84258711,"remaining_time":6.533353774},
{"learn":[10.94069562],"iteration":624,"passed_time":10.86146808,"remaining_time":6.516880849},
{"learn":[10.94069122],"iteration":625,"passed_time":10.87642771,"remaining_time":6.498057452},
{"learn":[10.94068682],"iteration":626,"passed_time":10.89079653,"remaining_time":6.478894904},
{"learn":[10.94068233],"iteration":627,"passed_time":10.91048848,"remaining_time":6.462900819},
{"learn":[10.94067793],"iteration":628,"passed_time":10.92499123,"remaining_time":6.443834258},
{"learn":[10.9406734],"iteration":629,"passed_time":10.9427057,"remaining_time":6.426668425},
{"learn":[10.940669],"iteration":630,"passed_time":10.95750237,"remaining_time":6.407794573},
{"learn":[10.94066328],"iteration":631,"passed_time":10.97516815,"remaining_time":6.390604237},
{"learn":[10.94065886],"iteration":632,"passed_time":10.99064723,"remaining_time":6.372144604},
{"learn":[10.94065446],"iteration":633,"passed_time":11.00509213,"remaining_time":6.35309735},
{"learn":[10.94065001],"iteration":634,"passed_time":11.02313162,"remaining_time":6.336130775},
{"learn":[10.94064561],"iteration":635,"passed_time":11.03891826,"remaining_time":6.317871456},
{"learn":[10.94064116],"iteration":636,"passed_time":11.0553402,"remaining_time":6.299981935},
{"learn":[10.94063607],"iteration":637,"passed_time":11.07327431,"remaining_time":6.282955017},
{"learn":[10.94063163],"iteration":638,"passed_time":11.09064477,"remaining_time":6.265606825},
{"learn":[10.94062718],"iteration":639,"passed_time":11.10912524,"remaining_time":6.248882945},
{"learn":[10.94062278],"iteration":640,"passed_time":11.12346545,"remaining_time":6.229834785},
{"learn":[10.94061838],"iteration":641,"passed_time":11.13805977,"remaining_time":6.210942986},
{"learn":[10.94061398],"iteration":642,"passed_time":11.15248357,"remaining_time":6.191969882},
{"learn":[10.94060938],"iteration":643,"passed_time":11.16800877,"remaining_time":6.173619757},
{"learn":[10.94060498],"iteration":644,"passed_time":11.18482491,"remaining_time":6.155988901},
{"learn":[10.94060058],"iteration":645,"passed_time":11.20068487,"remaining_time":6.137836602},
{"learn":[10.94059605],"iteration":646,"passed_time":11.2166067,"remaining_time":6.119725142},
{"learn":[10.94059152],"iteration":647,"passed_time":11.23353738,"remaining_time":6.102168451},
{"learn":[10.94058712],"iteration":648,"passed_time":11.25100111,"remaining_time":6.084901988},
{"learn":[10.94058272],"iteration":649,"passed_time":11.26974486,"remaining_time":6.068324157},
{"learn":[10.94057829],"iteration":650,"passed_time":11.28876675,"remaining_time":6.051888782},
{"learn":[10.94057388],"iteration":651,"passed_time":11.30543055,"remaining_time":6.03418686},
{"learn":[10.94056948],"iteration":652,"passed_time":11.32215699,"remaining_time":6.016521399},
{"learn":[10.94056499],"iteration":653,"passed_time":11.34071732,"remaining_time":5.999829039},
{"learn":[10.94056056],"iteration":654,"passed_time":11.35837655,"remaining_time":5.98265635},
{"learn":[10.9405553],"iteration":655,"passed_time":11.38297659,"remaining_time":5.96912187},
{"learn":[10.9405509],"iteration":656,"passed_time":11.39774514,"remaining_time":5.950420977},
{"learn":[10.94054562],"iteration":657,"passed_time":11.41611654,"remaining_time":5.933604644},
{"learn":[10.94054122],"iteration":658,"passed_time":11.4329437,"remaining_time":5.915984525},
{"learn":[10.94053682],"iteration":659,"passed_time":11.44957493,"remaining_time":5.898265875},
{"learn":[10.94053242],"iteration":660,"passed_time":11.46453953,"remaining_time":5.879695766},
{"learn":[10.94052795],"iteration":661,"passed_time":11.48128772,"remaining_time":5.862047202},
{"learn":[10.94052352],"iteration":662,"passed_time":11.49684962,"remaining_time":5.843798373},
{"learn":[10.94051838],"iteration":663,"passed_time":11.51392221,"remaining_time":5.826322085},
{"learn":[10.94051398],"iteration":664,"passed_time":11.52833637,"remaining_time":5.807507794},
{"learn":[10.94050958],"iteration":665,"passed_time":11.54257472,"remaining_time":5.788618552},
{"learn":[10.94050513],"iteration":666,"passed_time":11.55803051,"remaining_time":5.770351062},
{"learn":[10.94050059],"iteration":667,"passed_time":11.57850916,"remaining_time":5.754588387},
{"learn":[10.94049614],"iteration":668,"passed_time":11.5947474,"remaining_time":5.736713586},
{"learn":[10.94049173],"iteration":669,"passed_time":11.60928376,"remaining_time":5.718005434},
{"learn":[10.94048733],"iteration":670,"passed_time":11.62347465,"remaining_time":5.699140328},
{"learn":[10.94048215],"iteration":671,"passed_time":11.64160265,"remaining_time":5.682210818},
{"learn":[10.94047775],"iteration":672,"passed_time":11.65601982,"remaining_time":5.663474712},
{"learn":[10.94047335],"iteration":673,"passed_time":11.67016671,"remaining_time":5.644620692},
{"learn":[10.94046895],"iteration":674,"passed_time":11.68550507,"remaining_time":5.626354291},
{"learn":[10.94046455],"iteration":675,"passed_time":11.69984282,"remaining_time":5.607616975},
{"learn":[10.94046008],"iteration":676,"passed_time":11.71529191,"remaining_time":5.589422876},
{"learn":[10.94045567],"iteration":677,"passed_time":11.72945372,"remaining_time":5.570625515},
{"learn":[10.94045127],"iteration":678,"passed_time":11.74412989,"remaining_time":5.552084968},
{"learn":[10.94044687],"iteration":679,"passed_time":11.75988645,"remaining_time":5.53406421},
{"learn":[10.94044247],"iteration":680,"passed_time":11.77425351,"remaining_time":5.515399222},
{"learn":[10.94043806],"iteration":681,"passed_time":11.78845737,"remaining_time":5.496670739},
{"learn":[10.94043362],"iteration":682,"passed_time":11.80385858,"remaining_time":5.478511228},
{"learn":[10.94042909],"iteration":683,"passed_time":11.82333864,"remaining_time":5.462244167},
{"learn":[10.94042464],"iteration":684,"passed_time":11.84273132,"remaining_time":5.445927542},
{"learn":[10.94042024],"iteration":685,"passed_time":11.85716016,"remaining_time":5.427329871},
{"learn":[10.94041584],"iteration":686,"passed_time":11.87213291,"remaining_time":5.408992141},
{"learn":[10.94041144],"iteration":687,"passed_time":11.88760017,"remaining_time":5.390888448},
{"learn":[10.94040704],"iteration":688,"passed_time":11.9028431,"remaining_time":5.372691152},
{"learn":[10.94040253],"iteration":689,"passed_time":11.92191757,"remaining_time":5.356223835},
{"learn":[10.94039811],"iteration":690,"passed_time":11.93933783,"remaining_time":5.339009245},
{"learn":[10.94039362],"iteration":691,"passed_time":11.95616896,"remaining_time":5.321531851},
{"learn":[10.94038921],"iteration":692,"passed_time":11.97387614,"remaining_time":5.30444441},
{"learn":[10.9403846],"iteration":693,"passed_time":11.99217735,"remaining_time":5.287617104},
{"learn":[10.9403802],"iteration":694,"passed_time":12.00701791,"remaining_time":5.269266851},
{"learn":[10.94037568],"iteration":695,"passed_time":12.02879456,"remaining_time":5.253956244},
{"learn":[10.94037127],"iteration":696,"passed_time":12.04561845,"remaining_time":5.236474018},
{"learn":[10.94036686],"iteration":697,"passed_time":12.0617163,"remaining_time":5.218679545},
{"learn":[10.94036246],"iteration":698,"passed_time":12.07695228,"remaining_time":5.200518792},
{"learn":[10.94035732],"iteration":699,"passed_time":12.09280247,"remaining_time":5.182629631},
{"learn":[10.94035208],"iteration":700,"passed_time":12.11330168,"remaining_time":5.166729247},
{"learn":[10.94034675],"iteration":701,"passed_time":12.13444343,"remaining_time":5.15108852},
{"learn":[10.94034235],"iteration":702,"passed_time":12.1488548,"remaining_time":5.132588727},
{"learn":[10.94033795],"iteration":703,"passed_time":12.16327326,"remaining_time":5.114103529},
{"learn":[10.94033355],"iteration":704,"passed_time":12.18048004,"remaining_time":5.096796613},
{"learn":[10.9403278],"iteration":705,"passed_time":12.20274895,"remaining_time":5.081598006},
{"learn":[10.9403234],"iteration":706,"passed_time":12.21985675,"remaining_time":5.064240491},
{"learn":[10.94031897],"iteration":707,"passed_time":12.23871016,"remaining_time":5.047603626},
{"learn":[10.94031325],"iteration":708,"passed_time":12.26047943,"remaining_time":5.032157285},
{"learn":[10.94030813],"iteration":709,"passed_time":12.28000254,"remaining_time":5.015775686},
{"learn":[10.94030367],"iteration":710,"passed_time":12.29677016,"remaining_time":4.998265228},
{"learn":[10.94029927],"iteration":711,"passed_time":12.31302515,"remaining_time":4.980549498},
{"learn":[10.94029484],"iteration":712,"passed_time":12.32989669,"remaining_time":4.963086043},
{"learn":[10.94029044],"iteration":713,"passed_time":12.34489554,"remaining_time":4.944874123},
{"learn":[10.94028604],"iteration":714,"passed_time":12.36175419,"remaining_time":4.927412511},
{"learn":[10.94028158],"iteration":715,"passed_time":12.37824234,"remaining_time":4.909805621},
{"learn":[10.94027704],"iteration":716,"passed_time":12.39724337,"remaining_time":4.893193686},
{"learn":[10.9402725],"iteration":717,"passed_time":12.41420005,"remaining_time":4.875772166},
{"learn":[10.940268],"iteration":718,"passed_time":12.43180361,"remaining_time":4.858604748},
{"learn":[10.9402636],"iteration":719,"passed_time":12.44821222,"remaining_time":4.840971418},
{"learn":[10.9402592],"iteration":720,"passed_time":12.46456947,"remaining_time":4.823321612},
{"learn":[10.9402548],"iteration":721,"passed_time":12.48087486,"remaining_time":4.805655417},
{"learn":[10.9402504],"iteration":722,"passed_time":12.49562257,"remaining_time":4.787396199},
{"learn":[10.940246],"iteration":723,"passed_time":12.51007957,"remaining_time":4.769035858},
{"learn":[10.94024157],"iteration":724,"passed_time":12.52607238,"remaining_time":4.751268832},
{"learn":[10.94023698],"iteration":725,"passed_time":12.54194789,"remaining_time":4.733462428},
{"learn":[10.94023257],"iteration":726,"passed_time":12.55800686,"remaining_time":4.715730223},
{"learn":[10.94022809],"iteration":727,"passed_time":12.57549741,"remaining_time":4.698537494},
{"learn":[10.94022369],"iteration":728,"passed_time":12.58989838,"remaining_time":4.680195418},
{"learn":[10.94021929],"iteration":729,"passed_time":12.60601757,"remaining_time":4.66249965},
{"learn":[10.94021489],"iteration":730,"passed_time":12.62046835,"remaining_time":4.644194234},
{"learn":[10.94021049],"iteration":731,"passed_time":12.63509742,"remaining_time":4.625964628},
{"learn":[10.94020608],"iteration":732,"passed_time":12.65037209,"remaining_time":4.607980009},
{"learn":[10.94020156],"iteration":733,"passed_time":12.67087779,"remaining_time":4.591898491},
{"learn":[10.94019709],"iteration":734,"passed_time":12.68656459,"remaining_time":4.574067507},
{"learn":[10.94019267],"iteration":735,"passed_time":12.70395244,"remaining_time":4.556852505},
{"learn":[10.94018827],"iteration":736,"passed_time":12.7184796,"remaining_time":4.538616193},
{"learn":[10.94018379],"iteration":737,"passed_time":12.73447885,"remaining_time":4.520912547},
{"learn":[10.94017927],"iteration":738,"passed_time":12.75623029,"remaining_time":4.505245068},
{"learn":[10.94017487],"iteration":739,"passed_time":12.77094942,"remaining_time":4.487090337},
{"learn":[10.94017036],"iteration":740,"passed_time":12.78725101,"remaining_time":4.46949799},
{"learn":[10.94016594],"iteration":741,"passed_time":12.80671543,"remaining_time":4.453008868},
{"learn":[10.94016154],"iteration":742,"passed_time":12.82093299,"remaining_time":4.434696877},
{"learn":[10.94015714],"iteration":743,"passed_time":12.83588486,"remaining_time":4.416648556},
{"learn":[10.94015254],"iteration":744,"passed_time":12.85168483,"remaining_time":4.398898834},
{"learn":[10.94014802],"iteration":745,"passed_time":12.87351166,"remaining_time":4.383206382},
{"learn":[10.94014359],"iteration":746,"passed_time":12.88901465,"remaining_time":4.365355699},
{"learn":[10.94013919],"iteration":747,"passed_time":12.9034034,"remaining_time":4.347135904},
{"learn":[10.94013479],"iteration":748,"passed_time":12.91816954,"remaining_time":4.32905281},
{"learn":[10.94012971],"iteration":749,"passed_time":12.93419278,"remaining_time":4.311397592},
{"learn":[10.94012454],"iteration":750,"passed_time":12.9534106,"remaining_time":4.294805912},
{"learn":[10.94012013],"iteration":751,"passed_time":12.9687798,"remaining_time":4.276938019},
{"learn":[10.94011555],"iteration":752,"passed_time":12.98954363,"remaining_time":4.260846317},
{"learn":[10.94011115],"iteration":753,"passed_time":13.00395177,"remaining_time":4.242668615},
{"learn":[10.94010661],"iteration":754,"passed_time":13.02051951,"remaining_time":4.225201694},
{"learn":[10.94010221],"iteration":755,"passed_time":13.03514995,"remaining_time":4.207111889},
{"learn":[10.94009739],"iteration":756,"passed_time":13.05684522,"remaining_time":4.191299062},
{"learn":[10.94009297],"iteration":757,"passed_time":13.0744607,"remaining_time":4.174168192},
{"learn":[10.94008857],"iteration":758,"passed_time":13.09122381,"remaining_time":4.156765401},
{"learn":[10.94008417],"iteration":759,"passed_time":13.10796292,"remaining_time":4.139356712},
{"learn":[10.94007967],"iteration":760,"passed_time":13.12844293,"remaining_time":4.123124652},
{"learn":[10.94007527],"iteration":761,"passed_time":13.14600254,"remaining_time":4.105969298},
{"learn":[10.94007086],"iteration":762,"passed_time":13.16507859,"remaining_time":4.089283912},
{"learn":[10.94006641],"iteration":763,"passed_time":13.18371046,"remaining_time":4.072455064},
{"learn":[10.94006201],"iteration":764,"passed_time":13.19878205,"remaining_time":4.054527819},
{"learn":[10.94005761],"iteration":765,"passed_time":13.21353297,"remaining_time":4.03651007},
{"learn":[10.9400532],"iteration":766,"passed_time":13.22906329,"remaining_time":4.01873761},
{"learn":[10.9400488],"iteration":767,"passed_time":13.24735298,"remaining_time":4.001804547},
{"learn":[10.94004437],"iteration":768,"passed_time":13.26907901,"remaining_time":3.985900198},
{"learn":[10.94003997],"iteration":769,"passed_time":13.28537499,"remaining_time":3.968358762},
{"learn":[10.94003555],"iteration":770,"passed_time":13.30407821,"remaining_time":3.951535551},
{"learn":[10.94003091],"iteration":771,"passed_time":13.32308685,"remaining_time":3.934797671},
{"learn":[10.94002638],"iteration":772,"passed_time":13.34230369,"remaining_time":3.918115054},
{"learn":[10.94002185],"iteration":773,"passed_time":13.35848656,"remaining_time":3.900540003},
{"learn":[10.94001745],"iteration":774,"passed_time":13.37294397,"remaining_time":3.882467604},
{"learn":[10.94001223],"iteration":775,"passed_time":13.39175904,"remaining_time":3.865662404},
{"learn":[10.94000783],"iteration":776,"passed_time":13.40620309,"remaining_time":3.84759754},
{"learn":[10.94000343],"iteration":777,"passed_time":13.42077287,"remaining_time":3.829577863},
{"learn":[10.93999897],"iteration":778,"passed_time":13.43634074,"remaining_time":3.811850197},
{"learn":[10.93999386],"iteration":779,"passed_time":13.45547019,"remaining_time":3.795132617},
{"learn":[10.93998877],"iteration":780,"passed_time":13.47284406,"remaining_time":3.77791658},
{"learn":[10.93998437],"iteration":781,"passed_time":13.4906351,"remaining_time":3.760816434},
{"learn":[10.93997997],"iteration":782,"passed_time":13.50620917,"remaining_time":3.743100115},
{"learn":[10.93997468],"iteration":783,"passed_time":13.53021841,"remaining_time":3.727713235},
{"learn":[10.93996936],"iteration":784,"passed_time":13.55419546,"remaining_time":3.712295571},
{"learn":[10.93996496],"iteration":785,"passed_time":13.56998993,"remaining_time":3.694628303},
{"learn":[10.93995977],"iteration":786,"passed_time":13.59423012,"remaining_time":3.679251608},
{"learn":[10.93995537],"iteration":787,"passed_time":13.61160391,"remaining_time":3.662005114},
{"learn":[10.93995097],"iteration":788,"passed_time":13.62732463,"remaining_time":3.644316218},
{"learn":[10.9399465],"iteration":789,"passed_time":13.64442682,"remaining_time":3.626999534},
{"learn":[10.9399421],"iteration":790,"passed_time":13.66114718,"remaining_time":3.609582504},
{"learn":[10.9399377],"iteration":791,"passed_time":13.67640785,"remaining_time":3.591783881},
{"learn":[10.93993327],"iteration":792,"passed_time":13.69286891,"remaining_time":3.574304999},
{"learn":[10.93992864],"iteration":793,"passed_time":13.71148792,"remaining_time":3.557388555},
{"learn":[10.93992424],"iteration":794,"passed_time":13.72683173,"remaining_time":3.539623276},
{"learn":[10.93991906],"iteration":795,"passed_time":13.7452596,"remaining_time":3.522654471},
{"learn":[10.9399146],"iteration":796,"passed_time":13.76241964,"remaining_time":3.50535908},
{"learn":[10.93991014],"iteration":797,"passed_time":13.78158106,"remaining_time":3.488570644},
{"learn":[10.93990573],"iteration":798,"passed_time":13.79902915,"remaining_time":3.471345254},
{"learn":[10.93990132],"iteration":799,"passed_time":13.81770264,"remaining_time":3.454425661},
{"learn":[10.93989685],"iteration":800,"passed_time":13.83390022,"remaining_time":3.436886572},
{"learn":[10.93989241],"iteration":801,"passed_time":13.85031827,"remaining_time":3.419405259},
{"learn":[10.93988789],"iteration":802,"passed_time":13.86686929,"remaining_time":3.401959215},
{"learn":[10.93988348],"iteration":803,"passed_time":13.88299077,"remaining_time":3.384410685},
{"learn":[10.93987889],"iteration":804,"passed_time":13.90548541,"remaining_time":3.368409509},
{"learn":[10.93987442],"iteration":805,"passed_time":13.92250996,"remaining_time":3.351075599},
{"learn":[10.93986998],"iteration":806,"passed_time":13.93919902,"remaining_time":3.333662219},
{"learn":[10.93986554],"iteration":807,"passed_time":13.95583611,"remaining_time":3.316238283},
{"learn":[10.93986114],"iteration":808,"passed_time":13.97023418,"remaining_time":3.298287675},
{"learn":[10.93985665],"iteration":809,"passed_time":13.98969375,"remaining_time":3.281533101},
{"learn":[10.93985224],"iteration":810,"passed_time":14.00754069,"remaining_time":3.264396043},
{"learn":[10.93984784],"iteration":811,"passed_time":14.02286836,"remaining_time":3.246673956},
{"learn":[10.93984344],"iteration":812,"passed_time":14.03789593,"remaining_time":3.228888731},
{"learn":[10.93983832],"iteration":813,"passed_time":14.05505683,"remaining_time":3.211597752},
{"learn":[10.93983392],"iteration":814,"passed_time":14.06980476,"remaining_time":3.193759364},
{"learn":[10.93982952],"iteration":815,"passed_time":14.08448151,"remaining_time":3.175912497},
{"learn":[10.93982508],"iteration":816,"passed_time":14.10082553,"remaining_time":3.158446845},
{"learn":[10.93982053],"iteration":817,"passed_time":14.11917912,"remaining_time":3.141431051},
{"learn":[10.93981594],"iteration":818,"passed_time":14.13509141,"remaining_time":3.12387246},
{"learn":[10.93981083],"iteration":819,"passed_time":14.15114426,"remaining_time":3.106348739},
{"learn":[10.93980559],"iteration":820,"passed_time":14.16889992,"remaining_time":3.089199861},
{"learn":[10.93980119],"iteration":821,"passed_time":14.1849977,"remaining_time":3.0716905},
{"learn":[10.93979679],"iteration":822,"passed_time":14.20125057,"remaining_time":3.054217923},
{"learn":[10.93979239],"iteration":823,"passed_time":14.2165555,"remaining_time":3.036545834},
{"learn":[10.93978798],"iteration":824,"passed_time":14.2329751,"remaining_time":3.019115931},
{"learn":[10.9397828],"iteration":825,"passed_time":14.25613795,"remaining_time":3.003108963},
{"learn":[10.93977828],"iteration":826,"passed_time":14.27702148,"remaining_time":2.986607879},
{"learn":[10.9397731],"iteration":827,"passed_time":14.29490926,"remaining_time":2.969473904},
{"learn":[10.9397687],"iteration":828,"passed_time":14.31009725,"remaining_time":2.951781217},
{"learn":[10.9397643],"iteration":829,"passed_time":14.32521014,"remaining_time":2.934079185},
{"learn":[10.93975986],"iteration":830,"passed_time":14.34426405,"remaining_time":2.917184866},
{"learn":[10.93975546],"iteration":831,"passed_time":14.35938994,"remaining_time":2.8994922},
{"learn":[10.93974975],"iteration":832,"passed_time":14.37639432,"remaining_time":2.882182294},
{"learn":[10.93974533],"iteration":833,"passed_time":14.39922897,"remaining_time":2.866033583},
{"learn":[10.93974093],"iteration":834,"passed_time":14.41475572,"remaining_time":2.848424782},
{"learn":[10.93973653],"iteration":835,"passed_time":14.43166404,"remaining_time":2.831091989},
{"learn":[10.93973188],"iteration":836,"passed_time":14.44964666,"remaining_time":2.813969422},
{"learn":[10.93972743],"iteration":837,"passed_time":14.46836441,"remaining_time":2.796986914},
{"learn":[10.93972303],"iteration":838,"passed_time":14.48480822,"remaining_time":2.779563914},
{"learn":[10.93971835],"iteration":839,"passed_time":14.50738172,"remaining_time":2.763310804},
{"learn":[10.93971395],"iteration":840,"passed_time":14.52383646,"remaining_time":2.745885846},
{"learn":[10.93970952],"iteration":841,"passed_time":14.54466539,"remaining_time":2.729284003},
{"learn":[10.93970512],"iteration":842,"passed_time":14.56114415,"remaining_time":2.711861958},
{"learn":[10.93970072],"iteration":843,"passed_time":14.57674552,"remaining_time":2.694279978},
{"learn":[10.93969554],"iteration":844,"passed_time":14.59470481,"remaining_time":2.677135202},
{"learn":[10.93969105],"iteration":845,"passed_time":14.61577361,"remaining_time":2.660554535},
{"learn":[10.93968658],"iteration":846,"passed_time":14.63657123,"remaining_time":2.643914284},
{"learn":[10.93968206],"iteration":847,"passed_time":14.6572966,"remaining_time":2.627251278},
{"learn":[10.93967766],"iteration":848,"passed_time":14.67276832,"remaining_time":2.609644306},
{"learn":[10.93967326],"iteration":849,"passed_time":14.68787937,"remaining_time":2.591978712},
{"learn":[10.93966884],"iteration":850,"passed_time":14.7058846,"remaining_time":2.574825859},
{"learn":[10.93966444],"iteration":851,"passed_time":14.72114427,"remaining_time":2.557194076},
{"learn":[10.93965913],"iteration":852,"passed_time":14.74337705,"remaining_time":2.540769551},
{"learn":[10.93965473],"iteration":853,"passed_time":14.75988966,"remaining_time":2.523353502},
{"learn":[10.93965033],"iteration":854,"passed_time":14.77512606,"remaining_time":2.505723132},
{"learn":[10.93964593],"iteration":855,"passed_time":14.78958031,"remaining_time":2.487966781},
{"learn":[10.93964151],"iteration":856,"passed_time":14.80480414,"remaining_time":2.470346549},
{"learn":[10.93963711],"iteration":857,"passed_time":14.81971591,"remaining_time":2.452680256},
{"learn":[10.93963248],"iteration":858,"passed_time":14.84040584,"remaining_time":2.435968828},
{"learn":[10.93962808],"iteration":859,"passed_time":14.85534973,"remaining_time":2.418312746},
{"learn":[10.93962368],"iteration":860,"passed_time":14.8705113,"remaining_time":2.400698108},
{"learn":[10.93961851],"iteration":861,"passed_time":14.89187953,"remaining_time":2.384082802},
{"learn":[10.93961406],"iteration":862,"passed_time":14.90769088,"remaining_time":2.366574335},
{"learn":[10.93960966],"iteration":863,"passed_time":14.92259822,"remaining_time":2.348927497},
{"learn":[10.93960523],"iteration":864,"passed_time":14.93826903,"remaining_time":2.331406149},
{"learn":[10.93960067],"iteration":865,"passed_time":14.95756937,"remaining_time":2.314450688},
{"learn":[10.93959561],"iteration":866,"passed_time":14.975082,"remaining_time":2.297215578},
{"learn":[10.93959119],"iteration":867,"passed_time":14.99471217,"remaining_time":2.280301851},
{"learn":[10.93958671],"iteration":868,"passed_time":15.01371418,"remaining_time":2.263287178},
{"learn":[10.93958231],"iteration":869,"passed_time":15.02905021,"remaining_time":2.245720146},
{"learn":[10.93957791],"iteration":870,"passed_time":15.04404265,"remaining_time":2.22810735},
{"learn":[10.93957268],"iteration":871,"passed_time":15.06578813,"remaining_time":2.211491835},
{"learn":[10.93956828],"iteration":872,"passed_time":15.08285469,"remaining_time":2.194183902},
{"learn":[10.93956313],"iteration":873,"passed_time":15.1018931,"remaining_time":2.177160791},
{"learn":[10.93955873],"iteration":874,"passed_time":15.11847119,"remaining_time":2.159781598},
{"learn":[10.93955433],"iteration":875,"passed_time":15.13435855,"remaining_time":2.142306462},
{"learn":[10.93954994],"iteration":876,"passed_time":15.15054386,"remaining_time":2.124876734},
{"learn":[10.93954554],"iteration":877,"passed_time":15.1676387,"remaining_time":2.107576221},
{"learn":[10.93954114],"iteration":878,"passed_time":15.18353855,"remaining_time":2.090111678},
{"learn":[10.93953673],"iteration":879,"passed_time":15.20214033,"remaining_time":2.073019136},
{"learn":[10.93953227],"iteration":880,"passed_time":15.22095754,"remaining_time":2.055952267},
{"learn":[10.93952787],"iteration":881,"passed_time":15.23698556,"remaining_time":2.038508273},
{"learn":[10.93952335],"iteration":882,"passed_time":15.25716026,"remaining_time":2.021616931},
{"learn":[10.93951895],"iteration":883,"passed_time":15.27637098,"remaining_time":2.004591667},
{"learn":[10.93951455],"iteration":884,"passed_time":15.29644513,"remaining_time":1.987673661},
{"learn":[10.93951015],"iteration":885,"passed_time":15.3156205,"remaining_time":1.970632886},
{"learn":[10.93950558],"iteration":886,"passed_time":15.34421226,"remaining_time":1.954786906},
{"learn":[10.93950118],"iteration":887,"passed_time":15.3660716,"remaining_time":1.938063085},
{"learn":[10.93949675],"iteration":888,"passed_time":15.38729151,"remaining_time":1.921247871},
{"learn":[10.93949234],"iteration":889,"passed_time":15.4090622,"remaining_time":1.904490833},
{"learn":[10.93948795],"iteration":890,"passed_time":15.42781942,"remaining_time":1.88735389},
{"learn":[10.93948275],"iteration":891,"passed_time":15.45267165,"remaining_time":1.870951276},
{"learn":[10.93947835],"iteration":892,"passed_time":15.47223317,"remaining_time":1.8538958},
{"learn":[10.93947395],"iteration":893,"passed_time":15.49143056,"remaining_time":1.836791543},
{"learn":[10.93946865],"iteration":894,"passed_time":15.51938294,"remaining_time":1.820709731},
{"learn":[10.93946423],"iteration":895,"passed_time":15.53954448,"remaining_time":1.803697127},
{"learn":[10.93945982],"iteration":896,"passed_time":15.56270623,"remaining_time":1.787022009},
{"learn":[10.9394554],"iteration":897,"passed_time":15.58428285,"remaining_time":1.770152395},
{"learn":[10.939451],"iteration":898,"passed_time":15.60402582,"remaining_time":1.753066304},
{"learn":[10.93944648],"iteration":899,"passed_time":15.62899336,"remaining_time":1.736554818},
{"learn":[10.93944205],"iteration":900,"passed_time":15.64966363,"remaining_time":1.719552386},
{"learn":[10.93943761],"iteration":901,"passed_time":15.66984341,"remaining_time":1.70248853},
{"learn":[10.93943321],"iteration":902,"passed_time":15.68692794,"remaining_time":1.685085283},
{"learn":[10.93942868],"iteration":903,"passed_time":15.70440017,"remaining_time":1.667723912},
{"learn":[10.93942423],"iteration":904,"passed_time":15.72065865,"remaining_time":1.650234886},
{"learn":[10.93941982],"iteration":905,"passed_time":15.7362986,"remaining_time":1.632684403},
{"learn":[10.93941542],"iteration":906,"passed_time":15.75358549,"remaining_time":1.615307001},
{"learn":[10.939411],"iteration":907,"passed_time":15.77192671,"remaining_time":1.598036627},
{"learn":[10.93940579],"iteration":908,"passed_time":15.78947395,"remaining_time":1.580684411},
{"learn":[10.93940139],"iteration":909,"passed_time":15.80505867,"remaining_time":1.563137671},
{"learn":[10.93939699],"iteration":910,"passed_time":15.82038542,"remaining_time":1.545570036},
{"learn":[10.93939249],"iteration":911,"passed_time":15.83701211,"remaining_time":1.528132748},
{"learn":[10.93938806],"iteration":912,"passed_time":15.855205,"remaining_time":1.510846479},
{"learn":[10.93938366],"iteration":913,"passed_time":15.86983125,"remaining_time":1.493222634},
{"learn":[10.93937922],"iteration":914,"passed_time":15.885524,"remaining_time":1.475704415},
{"learn":[10.93937478],"iteration":915,"passed_time":15.90257623,"remaining_time":1.458314851},
{"learn":[10.93937038],"iteration":916,"passed_time":15.91826866,"remaining_time":1.440802943},
{"learn":[10.93936598],"iteration":917,"passed_time":15.93302135,"remaining_time":1.423211057},
{"learn":[10.93936158],"iteration":918,"passed_time":15.94843038,"remaining_time":1.4056832},
{"learn":[10.93935718],"iteration":919,"passed_time":15.96274063,"remaining_time":1.388064402},
{"learn":[10.93935197],"iteration":920,"passed_time":15.98201624,"remaining_time":1.370878701},
{"learn":[10.93934757],"iteration":921,"passed_time":15.99657877,"remaining_time":1.353289744},
{"learn":[10.93934317],"iteration":922,"passed_time":16.01162497,"remaining_time":1.335747695},
{"learn":[10.9393387],"iteration":923,"passed_time":16.02890894,"remaining_time":1.318395108},
{"learn":[10.9393343],"iteration":924,"passed_time":16.04338809,"remaining_time":1.300815251},
{"learn":[10.9393299],"iteration":925,"passed_time":16.05771436,"remaining_time":1.283229873},
{"learn":[10.9393255],"iteration":926,"passed_time":16.07220816,"remaining_time":1.26566472},
{"learn":[10.9393211],"iteration":927,"passed_time":16.08740262,"remaining_time":1.248160548},
{"learn":[10.9393167],"iteration":928,"passed_time":16.10240551,"remaining_time":1.230646707},
{"learn":[10.9393123],"iteration":929,"passed_time":16.11964646,"remaining_time":1.213306723},
{"learn":[10.9393079],"iteration":930,"passed_time":16.13909432,"remaining_time":1.196130514},
{"learn":[10.9393035],"iteration":931,"passed_time":16.15686063,"remaining_time":1.178826741},
{"learn":[10.93929911],"iteration":932,"passed_time":16.17349169,"remaining_time":1.161440454},
{"learn":[10.93929464],"iteration":933,"passed_time":16.19424474,"remaining_time":1.144347059},
{"learn":[10.93929024],"iteration":934,"passed_time":16.21022893,"remaining_time":1.126914311},
{"learn":[10.93928585],"iteration":935,"passed_time":16.22547414,"remaining_time":1.109434129},
{"learn":[10.93928129],"iteration":936,"passed_time":16.24655493,"remaining_time":1.092351079},
{"learn":[10.93927679],"iteration":937,"passed_time":16.26782127,"remaining_time":1.075271768},
{"learn":[10.93927162],"iteration":938,"passed_time":16.29039041,"remaining_time":1.058268174},
{"learn":[10.93926718],"iteration":939,"passed_time":16.31035028,"remaining_time":1.041086188},
{"learn":[10.93926275],"iteration":940,"passed_time":16.32804538,"remaining_time":1.023756299},
{"learn":[10.93925835],"iteration":941,"passed_time":16.34590474,"remaining_time":1.006435748},
{"learn":[10.93925374],"iteration":942,"passed_time":16.36935331,"remaining_time":0.9894518969},
{"learn":[10.93924932],"iteration":943,"passed_time":16.38632955,"remaining_time":0.9720703971},
{"learn":[10.9392448],"iteration":944,"passed_time":16.40624937,"remaining_time":0.9548610744},
{"learn":[10.93924019],"iteration":945,"passed_time":16.42344862,"remaining_time":0.9374907245},
{"learn":[10.93923572],"iteration":946,"passed_time":16.44358538,"remaining_time":0.9202851372},
{"learn":[10.93923128],"iteration":947,"passed_time":16.46112638,"remaining_time":0.9029309831},
{"learn":[10.93922678],"iteration":948,"passed_time":16.48151865,"remaining_time":0.8857296641},
{"learn":[10.93922238],"iteration":949,"passed_time":16.49630785,"remaining_time":0.8682267289},
{"learn":[10.93921798],"iteration":950,"passed_time":16.51128042,"remaining_time":0.850738949},
{"learn":[10.93921358],"iteration":951,"passed_time":16.52804526,"remaining_time":0.8333468198},
{"learn":[10.93920913],"iteration":952,"passed_time":16.54336232,"remaining_time":0.8158846055},
{"learn":[10.93920454],"iteration":953,"passed_time":16.55881124,"remaining_time":0.7984332464},
{"learn":[10.93920008],"iteration":954,"passed_time":16.57563261,"remaining_time":0.7810507513},
{"learn":[10.93919569],"iteration":955,"passed_time":16.59036856,"remaining_time":0.7635734483},
{"learn":[10.93919128],"iteration":956,"passed_time":16.60576311,"remaining_time":0.7461314667},
{"learn":[10.93918688],"iteration":957,"passed_time":16.62034593,"remaining_time":0.7286581722},
{"learn":[10.93918248],"iteration":958,"passed_time":16.63684104,"remaining_time":0.7112726618},
{"learn":[10.93917808],"iteration":959,"passed_time":16.65330364,"remaining_time":0.6938876517},
{"learn":[10.93917368],"iteration":960,"passed_time":16.66774927,"remaining_time":0.6764227072},
{"learn":[10.93916929],"iteration":961,"passed_time":16.68212251,"remaining_time":0.6589611801},
{"learn":[10.93916479],"iteration":962,"passed_time":16.69991993,"remaining_time":0.6416376299},
{"learn":[10.93916039],"iteration":963,"passed_time":16.71437673,"remaining_time":0.6241883425},
{"learn":[10.93915588],"iteration":964,"passed_time":16.73191076,"remaining_time":0.606856867},
{"learn":[10.93915143],"iteration":965,"passed_time":16.74928624,"remaining_time":0.5895193913},
{"learn":[10.93914694],"iteration":966,"passed_time":16.76613697,"remaining_time":0.5721639298},
{"learn":[10.93914255],"iteration":967,"passed_time":16.78169547,"remaining_time":0.5547667923},
{"learn":[10.93913815],"iteration":968,"passed_time":16.79622301,"remaining_time":0.5373404677},
{"learn":[10.93913302],"iteration":969,"passed_time":16.81419118,"remaining_time":0.5200265313},
{"learn":[10.93912857],"iteration":970,"passed_time":16.82961218,"remaining_time":0.5026351733},
{"learn":[10.93912417],"iteration":971,"passed_time":16.84548622,"remaining_time":0.48526092},
{"learn":[10.93911955],"iteration":972,"passed_time":16.86442983,"remaining_time":0.4679749286},
{"learn":[10.93911437],"iteration":973,"passed_time":16.88221486,"remaining_time":0.450654606},
{"learn":[10.93910997],"iteration":974,"passed_time":16.89799484,"remaining_time":0.433281919},
{"learn":[10.93910553],"iteration":975,"passed_time":16.91477635,"remaining_time":0.4159371234},
{"learn":[10.93910114],"iteration":976,"passed_time":16.92951165,"remaining_time":0.3985453101},
{"learn":[10.93909666],"iteration":977,"passed_time":16.94707729,"remaining_time":0.3812225976},
{"learn":[10.93909147],"iteration":978,"passed_time":16.96311879,"remaining_time":0.3638666952},
{"learn":[10.93908686],"iteration":979,"passed_time":16.97981174,"remaining_time":0.3465267703},
{"learn":[10.93908246],"iteration":980,"passed_time":16.9944157,"remaining_time":0.3291477047},
{"learn":[10.939078],"iteration":981,"passed_time":17.00985447,"remaining_time":0.3117895931},
{"learn":[10.93907357],"iteration":982,"passed_time":17.02678866,"remaining_time":0.2944612484},
{"learn":[10.93906917],"iteration":983,"passed_time":17.04114396,"remaining_time":0.2770917716},
{"learn":[10.93906477],"iteration":984,"passed_time":17.05738628,"remaining_time":0.2597571514},
{"learn":[10.93906037],"iteration":985,"passed_time":17.07555755,"remaining_time":0.2424521356},
{"learn":[10.93905597],"iteration":986,"passed_time":17.09081461,"remaining_time":0.2251069807},
{"learn":[10.9390515],"iteration":987,"passed_time":17.10938651,"remaining_time":0.2078063139},
{"learn":[10.939047],"iteration":988,"passed_time":17.12698383,"remaining_time":0.1904922368},
{"learn":[10.9390424],"iteration":989,"passed_time":17.14263986,"remaining_time":0.1731579784},
{"learn":[10.93903801],"iteration":990,"passed_time":17.15823383,"remaining_time":0.1558265434},
{"learn":[10.93903361],"iteration":991,"passed_time":17.17565048,"remaining_time":0.1385133103},
{"learn":[10.93902921],"iteration":992,"passed_time":17.19147651,"remaining_time":0.1211886562},
{"learn":[10.93902481],"iteration":993,"passed_time":17.20581698,"remaining_time":0.1038580502},
{"learn":[10.93901965],"iteration":994,"passed_time":17.22168842,"remaining_time":0.08654114783},
{"learn":[10.93901493],"iteration":995,"passed_time":17.24200081,"remaining_time":0.06924498318},
{"learn":[10.93901053],"iteration":996,"passed_time":17.25923475,"remaining_time":0.05193350475},
{"learn":[10.93900613],"iteration":997,"passed_time":17.27727475,"remaining_time":0.03462379709},
{"learn":[10.93900173],"iteration":998,"passed_time":17.29488157,"remaining_time":0.01731219377},
{"learn":[10.93899726],"iteration":999,"passed_time":17.31758855,"remaining_time":0}
]}